package facade.characters.wmedef;

import wm.WME;

public class PostBeatMixinInfoWME extends WME
{
    private int beatGGreetsP;
    private int beatArtistAdv;
    private int beatExplDatAnniv;
    private int beatFAskDrink;
    private int beatRockyMarriage;
    private int beatRockyMarriage_WorkTable;
    private int beatPhoneCall;
    private boolean bGGreetsP;
    private boolean bAA_decorating_txnIn;
    private boolean bAA_decorating_txnOut;
    private boolean bAA_decorating_styleApt;
    private boolean bAA_decorating_couch;
    private boolean bAA_decorating_armoire;
    private boolean bAA_decorating_trinkets;
    private boolean bAA_decorating_paintings;
    private boolean bAA_decorating_weddingPicture;
    private boolean bAA_decorating_view;
    private boolean bAA_decorating_sideTable;
    private boolean bAA_decorating_rug;
    private boolean bExplDatAnniv;
    private boolean bRM_Italy;
    private boolean bFAskDrinks;
    private boolean bPhoneCall;
    
    public synchronized int getBeatGGreetsP() {
        return this.beatGGreetsP;
    }
    
    public void setBeatGGreetsP(final int p0) {
        // 
        // This method could not be decompiled.
        // 
        // Original Bytecode:
        // 
        //     3: aload_3        
        //     4: monitorexit    
        //     5: athrow         
        //     6: aload_0        
        //     7: dup            
        //     8: astore_3       
        //     9: monitorenter   
        //    10: aload_0        
        //    11: getfield        facade/characters/wmedef/PostBeatMixinInfoWME.beatGGreetsP:I
        //    14: istore_2       
        //    15: aload_0        
        //    16: iload_1        
        //    17: putfield        facade/characters/wmedef/PostBeatMixinInfoWME.beatGGreetsP:I
        //    20: aload_3        
        //    21: monitorexit    
        //    22: aload_0        
        //    23: getfield        facade/characters/wmedef/PostBeatMixinInfoWME.__support:Ljava/beans/PropertyChangeSupport;
        //    26: ldc             "beatGGreetsP"
        //    28: iload_2        
        //    29: iload_1        
        //    30: invokevirtual   java/beans/PropertyChangeSupport.firePropertyChange:(Ljava/lang/String;II)V
        //    33: return         
        //    Exceptions:
        //  Try           Handler
        //  Start  End    Start  End    Type
        //  -----  -----  -----  -----  ----
        //  3      5      3      6      Any
        //  10     22     3      6      Any
        // 
        // The error that occurred was:
        // 
        // java.util.ConcurrentModificationException
        //     at java.util.ArrayList$Itr.checkForComodification(Unknown Source)
        //     at java.util.ArrayList$Itr.next(Unknown Source)
        //     at com.strobel.decompiler.ast.AstBuilder.convertLocalVariables(AstBuilder.java:2863)
        //     at com.strobel.decompiler.ast.AstBuilder.performStackAnalysis(AstBuilder.java:2445)
        //     at com.strobel.decompiler.ast.AstBuilder.build(AstBuilder.java:108)
        //     at com.strobel.decompiler.languages.java.ast.AstMethodBodyBuilder.createMethodBody(AstMethodBodyBuilder.java:211)
        //     at com.strobel.decompiler.languages.java.ast.AstMethodBodyBuilder.createMethodBody(AstMethodBodyBuilder.java:99)
        //     at com.strobel.decompiler.languages.java.ast.AstBuilder.createMethodBody(AstBuilder.java:782)
        //     at com.strobel.decompiler.languages.java.ast.AstBuilder.createMethod(AstBuilder.java:675)
        //     at com.strobel.decompiler.languages.java.ast.AstBuilder.addTypeMembers(AstBuilder.java:552)
        //     at com.strobel.decompiler.languages.java.ast.AstBuilder.createTypeCore(AstBuilder.java:519)
        //     at com.strobel.decompiler.languages.java.ast.AstBuilder.createTypeNoCache(AstBuilder.java:161)
        //     at com.strobel.decompiler.languages.java.ast.AstBuilder.createType(AstBuilder.java:150)
        //     at com.strobel.decompiler.languages.java.ast.AstBuilder.addType(AstBuilder.java:125)
        //     at com.strobel.decompiler.languages.java.JavaLanguage.buildAst(JavaLanguage.java:71)
        //     at com.strobel.decompiler.languages.java.JavaLanguage.decompileType(JavaLanguage.java:59)
        //     at com.strobel.decompiler.DecompilerDriver.decompileType(DecompilerDriver.java:330)
        //     at com.strobel.decompiler.DecompilerDriver.decompileJar(DecompilerDriver.java:251)
        //     at com.strobel.decompiler.DecompilerDriver.main(DecompilerDriver.java:126)
        // 
        throw new IllegalStateException("An error occurred while decompiling this method.");
    }
    
    public synchronized int getBeatArtistAdv() {
        return this.beatArtistAdv;
    }
    
    public void setBeatArtistAdv(final int p0) {
        // 
        // This method could not be decompiled.
        // 
        // Original Bytecode:
        // 
        //     3: aload_3        
        //     4: monitorexit    
        //     5: athrow         
        //     6: aload_0        
        //     7: dup            
        //     8: astore_3       
        //     9: monitorenter   
        //    10: aload_0        
        //    11: getfield        facade/characters/wmedef/PostBeatMixinInfoWME.beatArtistAdv:I
        //    14: istore_2       
        //    15: aload_0        
        //    16: iload_1        
        //    17: putfield        facade/characters/wmedef/PostBeatMixinInfoWME.beatArtistAdv:I
        //    20: aload_3        
        //    21: monitorexit    
        //    22: aload_0        
        //    23: getfield        facade/characters/wmedef/PostBeatMixinInfoWME.__support:Ljava/beans/PropertyChangeSupport;
        //    26: ldc             "beatArtistAdv"
        //    28: iload_2        
        //    29: iload_1        
        //    30: invokevirtual   java/beans/PropertyChangeSupport.firePropertyChange:(Ljava/lang/String;II)V
        //    33: return         
        //    Exceptions:
        //  Try           Handler
        //  Start  End    Start  End    Type
        //  -----  -----  -----  -----  ----
        //  3      5      3      6      Any
        //  10     22     3      6      Any
        // 
        // The error that occurred was:
        // 
        // java.util.ConcurrentModificationException
        //     at java.util.ArrayList$Itr.checkForComodification(Unknown Source)
        //     at java.util.ArrayList$Itr.next(Unknown Source)
        //     at com.strobel.decompiler.ast.AstBuilder.convertLocalVariables(AstBuilder.java:2863)
        //     at com.strobel.decompiler.ast.AstBuilder.performStackAnalysis(AstBuilder.java:2445)
        //     at com.strobel.decompiler.ast.AstBuilder.build(AstBuilder.java:108)
        //     at com.strobel.decompiler.languages.java.ast.AstMethodBodyBuilder.createMethodBody(AstMethodBodyBuilder.java:211)
        //     at com.strobel.decompiler.languages.java.ast.AstMethodBodyBuilder.createMethodBody(AstMethodBodyBuilder.java:99)
        //     at com.strobel.decompiler.languages.java.ast.AstBuilder.createMethodBody(AstBuilder.java:782)
        //     at com.strobel.decompiler.languages.java.ast.AstBuilder.createMethod(AstBuilder.java:675)
        //     at com.strobel.decompiler.languages.java.ast.AstBuilder.addTypeMembers(AstBuilder.java:552)
        //     at com.strobel.decompiler.languages.java.ast.AstBuilder.createTypeCore(AstBuilder.java:519)
        //     at com.strobel.decompiler.languages.java.ast.AstBuilder.createTypeNoCache(AstBuilder.java:161)
        //     at com.strobel.decompiler.languages.java.ast.AstBuilder.createType(AstBuilder.java:150)
        //     at com.strobel.decompiler.languages.java.ast.AstBuilder.addType(AstBuilder.java:125)
        //     at com.strobel.decompiler.languages.java.JavaLanguage.buildAst(JavaLanguage.java:71)
        //     at com.strobel.decompiler.languages.java.JavaLanguage.decompileType(JavaLanguage.java:59)
        //     at com.strobel.decompiler.DecompilerDriver.decompileType(DecompilerDriver.java:330)
        //     at com.strobel.decompiler.DecompilerDriver.decompileJar(DecompilerDriver.java:251)
        //     at com.strobel.decompiler.DecompilerDriver.main(DecompilerDriver.java:126)
        // 
        throw new IllegalStateException("An error occurred while decompiling this method.");
    }
    
    public synchronized int getBeatExplDatAnniv() {
        return this.beatExplDatAnniv;
    }
    
    public void setBeatExplDatAnniv(final int p0) {
        // 
        // This method could not be decompiled.
        // 
        // Original Bytecode:
        // 
        //     3: aload_3        
        //     4: monitorexit    
        //     5: athrow         
        //     6: aload_0        
        //     7: dup            
        //     8: astore_3       
        //     9: monitorenter   
        //    10: aload_0        
        //    11: getfield        facade/characters/wmedef/PostBeatMixinInfoWME.beatExplDatAnniv:I
        //    14: istore_2       
        //    15: aload_0        
        //    16: iload_1        
        //    17: putfield        facade/characters/wmedef/PostBeatMixinInfoWME.beatExplDatAnniv:I
        //    20: aload_3        
        //    21: monitorexit    
        //    22: aload_0        
        //    23: getfield        facade/characters/wmedef/PostBeatMixinInfoWME.__support:Ljava/beans/PropertyChangeSupport;
        //    26: ldc             "beatExplDatAnniv"
        //    28: iload_2        
        //    29: iload_1        
        //    30: invokevirtual   java/beans/PropertyChangeSupport.firePropertyChange:(Ljava/lang/String;II)V
        //    33: return         
        //    Exceptions:
        //  Try           Handler
        //  Start  End    Start  End    Type
        //  -----  -----  -----  -----  ----
        //  3      5      3      6      Any
        //  10     22     3      6      Any
        // 
        // The error that occurred was:
        // 
        // java.util.ConcurrentModificationException
        //     at java.util.ArrayList$Itr.checkForComodification(Unknown Source)
        //     at java.util.ArrayList$Itr.next(Unknown Source)
        //     at com.strobel.decompiler.ast.AstBuilder.convertLocalVariables(AstBuilder.java:2863)
        //     at com.strobel.decompiler.ast.AstBuilder.performStackAnalysis(AstBuilder.java:2445)
        //     at com.strobel.decompiler.ast.AstBuilder.build(AstBuilder.java:108)
        //     at com.strobel.decompiler.languages.java.ast.AstMethodBodyBuilder.createMethodBody(AstMethodBodyBuilder.java:211)
        //     at com.strobel.decompiler.languages.java.ast.AstMethodBodyBuilder.createMethodBody(AstMethodBodyBuilder.java:99)
        //     at com.strobel.decompiler.languages.java.ast.AstBuilder.createMethodBody(AstBuilder.java:782)
        //     at com.strobel.decompiler.languages.java.ast.AstBuilder.createMethod(AstBuilder.java:675)
        //     at com.strobel.decompiler.languages.java.ast.AstBuilder.addTypeMembers(AstBuilder.java:552)
        //     at com.strobel.decompiler.languages.java.ast.AstBuilder.createTypeCore(AstBuilder.java:519)
        //     at com.strobel.decompiler.languages.java.ast.AstBuilder.createTypeNoCache(AstBuilder.java:161)
        //     at com.strobel.decompiler.languages.java.ast.AstBuilder.createType(AstBuilder.java:150)
        //     at com.strobel.decompiler.languages.java.ast.AstBuilder.addType(AstBuilder.java:125)
        //     at com.strobel.decompiler.languages.java.JavaLanguage.buildAst(JavaLanguage.java:71)
        //     at com.strobel.decompiler.languages.java.JavaLanguage.decompileType(JavaLanguage.java:59)
        //     at com.strobel.decompiler.DecompilerDriver.decompileType(DecompilerDriver.java:330)
        //     at com.strobel.decompiler.DecompilerDriver.decompileJar(DecompilerDriver.java:251)
        //     at com.strobel.decompiler.DecompilerDriver.main(DecompilerDriver.java:126)
        // 
        throw new IllegalStateException("An error occurred while decompiling this method.");
    }
    
    public synchronized int getBeatFAskDrink() {
        return this.beatFAskDrink;
    }
    
    public void setBeatFAskDrink(final int p0) {
        // 
        // This method could not be decompiled.
        // 
        // Original Bytecode:
        // 
        //     3: aload_3        
        //     4: monitorexit    
        //     5: athrow         
        //     6: aload_0        
        //     7: dup            
        //     8: astore_3       
        //     9: monitorenter   
        //    10: aload_0        
        //    11: getfield        facade/characters/wmedef/PostBeatMixinInfoWME.beatFAskDrink:I
        //    14: istore_2       
        //    15: aload_0        
        //    16: iload_1        
        //    17: putfield        facade/characters/wmedef/PostBeatMixinInfoWME.beatFAskDrink:I
        //    20: aload_3        
        //    21: monitorexit    
        //    22: aload_0        
        //    23: getfield        facade/characters/wmedef/PostBeatMixinInfoWME.__support:Ljava/beans/PropertyChangeSupport;
        //    26: ldc             "beatFAskDrink"
        //    28: iload_2        
        //    29: iload_1        
        //    30: invokevirtual   java/beans/PropertyChangeSupport.firePropertyChange:(Ljava/lang/String;II)V
        //    33: return         
        //    Exceptions:
        //  Try           Handler
        //  Start  End    Start  End    Type
        //  -----  -----  -----  -----  ----
        //  3      5      3      6      Any
        //  10     22     3      6      Any
        // 
        // The error that occurred was:
        // 
        // java.util.ConcurrentModificationException
        //     at java.util.ArrayList$Itr.checkForComodification(Unknown Source)
        //     at java.util.ArrayList$Itr.next(Unknown Source)
        //     at com.strobel.decompiler.ast.AstBuilder.convertLocalVariables(AstBuilder.java:2863)
        //     at com.strobel.decompiler.ast.AstBuilder.performStackAnalysis(AstBuilder.java:2445)
        //     at com.strobel.decompiler.ast.AstBuilder.build(AstBuilder.java:108)
        //     at com.strobel.decompiler.languages.java.ast.AstMethodBodyBuilder.createMethodBody(AstMethodBodyBuilder.java:211)
        //     at com.strobel.decompiler.languages.java.ast.AstMethodBodyBuilder.createMethodBody(AstMethodBodyBuilder.java:99)
        //     at com.strobel.decompiler.languages.java.ast.AstBuilder.createMethodBody(AstBuilder.java:782)
        //     at com.strobel.decompiler.languages.java.ast.AstBuilder.createMethod(AstBuilder.java:675)
        //     at com.strobel.decompiler.languages.java.ast.AstBuilder.addTypeMembers(AstBuilder.java:552)
        //     at com.strobel.decompiler.languages.java.ast.AstBuilder.createTypeCore(AstBuilder.java:519)
        //     at com.strobel.decompiler.languages.java.ast.AstBuilder.createTypeNoCache(AstBuilder.java:161)
        //     at com.strobel.decompiler.languages.java.ast.AstBuilder.createType(AstBuilder.java:150)
        //     at com.strobel.decompiler.languages.java.ast.AstBuilder.addType(AstBuilder.java:125)
        //     at com.strobel.decompiler.languages.java.JavaLanguage.buildAst(JavaLanguage.java:71)
        //     at com.strobel.decompiler.languages.java.JavaLanguage.decompileType(JavaLanguage.java:59)
        //     at com.strobel.decompiler.DecompilerDriver.decompileType(DecompilerDriver.java:330)
        //     at com.strobel.decompiler.DecompilerDriver.decompileJar(DecompilerDriver.java:251)
        //     at com.strobel.decompiler.DecompilerDriver.main(DecompilerDriver.java:126)
        // 
        throw new IllegalStateException("An error occurred while decompiling this method.");
    }
    
    public synchronized int getBeatRockyMarriage() {
        return this.beatRockyMarriage;
    }
    
    public void setBeatRockyMarriage(final int p0) {
        // 
        // This method could not be decompiled.
        // 
        // Original Bytecode:
        // 
        //     3: aload_3        
        //     4: monitorexit    
        //     5: athrow         
        //     6: aload_0        
        //     7: dup            
        //     8: astore_3       
        //     9: monitorenter   
        //    10: aload_0        
        //    11: getfield        facade/characters/wmedef/PostBeatMixinInfoWME.beatRockyMarriage:I
        //    14: istore_2       
        //    15: aload_0        
        //    16: iload_1        
        //    17: putfield        facade/characters/wmedef/PostBeatMixinInfoWME.beatRockyMarriage:I
        //    20: aload_3        
        //    21: monitorexit    
        //    22: aload_0        
        //    23: getfield        facade/characters/wmedef/PostBeatMixinInfoWME.__support:Ljava/beans/PropertyChangeSupport;
        //    26: ldc             "beatRockyMarriage"
        //    28: iload_2        
        //    29: iload_1        
        //    30: invokevirtual   java/beans/PropertyChangeSupport.firePropertyChange:(Ljava/lang/String;II)V
        //    33: return         
        //    Exceptions:
        //  Try           Handler
        //  Start  End    Start  End    Type
        //  -----  -----  -----  -----  ----
        //  3      5      3      6      Any
        //  10     22     3      6      Any
        // 
        // The error that occurred was:
        // 
        // java.util.ConcurrentModificationException
        //     at java.util.ArrayList$Itr.checkForComodification(Unknown Source)
        //     at java.util.ArrayList$Itr.next(Unknown Source)
        //     at com.strobel.decompiler.ast.AstBuilder.convertLocalVariables(AstBuilder.java:2863)
        //     at com.strobel.decompiler.ast.AstBuilder.performStackAnalysis(AstBuilder.java:2445)
        //     at com.strobel.decompiler.ast.AstBuilder.build(AstBuilder.java:108)
        //     at com.strobel.decompiler.languages.java.ast.AstMethodBodyBuilder.createMethodBody(AstMethodBodyBuilder.java:211)
        //     at com.strobel.decompiler.languages.java.ast.AstMethodBodyBuilder.createMethodBody(AstMethodBodyBuilder.java:99)
        //     at com.strobel.decompiler.languages.java.ast.AstBuilder.createMethodBody(AstBuilder.java:782)
        //     at com.strobel.decompiler.languages.java.ast.AstBuilder.createMethod(AstBuilder.java:675)
        //     at com.strobel.decompiler.languages.java.ast.AstBuilder.addTypeMembers(AstBuilder.java:552)
        //     at com.strobel.decompiler.languages.java.ast.AstBuilder.createTypeCore(AstBuilder.java:519)
        //     at com.strobel.decompiler.languages.java.ast.AstBuilder.createTypeNoCache(AstBuilder.java:161)
        //     at com.strobel.decompiler.languages.java.ast.AstBuilder.createType(AstBuilder.java:150)
        //     at com.strobel.decompiler.languages.java.ast.AstBuilder.addType(AstBuilder.java:125)
        //     at com.strobel.decompiler.languages.java.JavaLanguage.buildAst(JavaLanguage.java:71)
        //     at com.strobel.decompiler.languages.java.JavaLanguage.decompileType(JavaLanguage.java:59)
        //     at com.strobel.decompiler.DecompilerDriver.decompileType(DecompilerDriver.java:330)
        //     at com.strobel.decompiler.DecompilerDriver.decompileJar(DecompilerDriver.java:251)
        //     at com.strobel.decompiler.DecompilerDriver.main(DecompilerDriver.java:126)
        // 
        throw new IllegalStateException("An error occurred while decompiling this method.");
    }
    
    public synchronized int getBeatRockyMarriage_WorkTable() {
        return this.beatRockyMarriage_WorkTable;
    }
    
    public void setBeatRockyMarriage_WorkTable(final int p0) {
        // 
        // This method could not be decompiled.
        // 
        // Original Bytecode:
        // 
        //     3: aload_3        
        //     4: monitorexit    
        //     5: athrow         
        //     6: aload_0        
        //     7: dup            
        //     8: astore_3       
        //     9: monitorenter   
        //    10: aload_0        
        //    11: getfield        facade/characters/wmedef/PostBeatMixinInfoWME.beatRockyMarriage_WorkTable:I
        //    14: istore_2       
        //    15: aload_0        
        //    16: iload_1        
        //    17: putfield        facade/characters/wmedef/PostBeatMixinInfoWME.beatRockyMarriage_WorkTable:I
        //    20: aload_3        
        //    21: monitorexit    
        //    22: aload_0        
        //    23: getfield        facade/characters/wmedef/PostBeatMixinInfoWME.__support:Ljava/beans/PropertyChangeSupport;
        //    26: ldc             "beatRockyMarriage_WorkTable"
        //    28: iload_2        
        //    29: iload_1        
        //    30: invokevirtual   java/beans/PropertyChangeSupport.firePropertyChange:(Ljava/lang/String;II)V
        //    33: return         
        //    Exceptions:
        //  Try           Handler
        //  Start  End    Start  End    Type
        //  -----  -----  -----  -----  ----
        //  3      5      3      6      Any
        //  10     22     3      6      Any
        // 
        // The error that occurred was:
        // 
        // java.util.ConcurrentModificationException
        //     at java.util.ArrayList$Itr.checkForComodification(Unknown Source)
        //     at java.util.ArrayList$Itr.next(Unknown Source)
        //     at com.strobel.decompiler.ast.AstBuilder.convertLocalVariables(AstBuilder.java:2863)
        //     at com.strobel.decompiler.ast.AstBuilder.performStackAnalysis(AstBuilder.java:2445)
        //     at com.strobel.decompiler.ast.AstBuilder.build(AstBuilder.java:108)
        //     at com.strobel.decompiler.languages.java.ast.AstMethodBodyBuilder.createMethodBody(AstMethodBodyBuilder.java:211)
        //     at com.strobel.decompiler.languages.java.ast.AstMethodBodyBuilder.createMethodBody(AstMethodBodyBuilder.java:99)
        //     at com.strobel.decompiler.languages.java.ast.AstBuilder.createMethodBody(AstBuilder.java:782)
        //     at com.strobel.decompiler.languages.java.ast.AstBuilder.createMethod(AstBuilder.java:675)
        //     at com.strobel.decompiler.languages.java.ast.AstBuilder.addTypeMembers(AstBuilder.java:552)
        //     at com.strobel.decompiler.languages.java.ast.AstBuilder.createTypeCore(AstBuilder.java:519)
        //     at com.strobel.decompiler.languages.java.ast.AstBuilder.createTypeNoCache(AstBuilder.java:161)
        //     at com.strobel.decompiler.languages.java.ast.AstBuilder.createType(AstBuilder.java:150)
        //     at com.strobel.decompiler.languages.java.ast.AstBuilder.addType(AstBuilder.java:125)
        //     at com.strobel.decompiler.languages.java.JavaLanguage.buildAst(JavaLanguage.java:71)
        //     at com.strobel.decompiler.languages.java.JavaLanguage.decompileType(JavaLanguage.java:59)
        //     at com.strobel.decompiler.DecompilerDriver.decompileType(DecompilerDriver.java:330)
        //     at com.strobel.decompiler.DecompilerDriver.decompileJar(DecompilerDriver.java:251)
        //     at com.strobel.decompiler.DecompilerDriver.main(DecompilerDriver.java:126)
        // 
        throw new IllegalStateException("An error occurred while decompiling this method.");
    }
    
    public synchronized int getBeatPhoneCall() {
        return this.beatPhoneCall;
    }
    
    public void setBeatPhoneCall(final int p0) {
        // 
        // This method could not be decompiled.
        // 
        // Original Bytecode:
        // 
        //     3: aload_3        
        //     4: monitorexit    
        //     5: athrow         
        //     6: aload_0        
        //     7: dup            
        //     8: astore_3       
        //     9: monitorenter   
        //    10: aload_0        
        //    11: getfield        facade/characters/wmedef/PostBeatMixinInfoWME.beatPhoneCall:I
        //    14: istore_2       
        //    15: aload_0        
        //    16: iload_1        
        //    17: putfield        facade/characters/wmedef/PostBeatMixinInfoWME.beatPhoneCall:I
        //    20: aload_3        
        //    21: monitorexit    
        //    22: aload_0        
        //    23: getfield        facade/characters/wmedef/PostBeatMixinInfoWME.__support:Ljava/beans/PropertyChangeSupport;
        //    26: ldc             "beatPhoneCall"
        //    28: iload_2        
        //    29: iload_1        
        //    30: invokevirtual   java/beans/PropertyChangeSupport.firePropertyChange:(Ljava/lang/String;II)V
        //    33: return         
        //    Exceptions:
        //  Try           Handler
        //  Start  End    Start  End    Type
        //  -----  -----  -----  -----  ----
        //  3      5      3      6      Any
        //  10     22     3      6      Any
        // 
        // The error that occurred was:
        // 
        // java.util.ConcurrentModificationException
        //     at java.util.ArrayList$Itr.checkForComodification(Unknown Source)
        //     at java.util.ArrayList$Itr.next(Unknown Source)
        //     at com.strobel.decompiler.ast.AstBuilder.convertLocalVariables(AstBuilder.java:2863)
        //     at com.strobel.decompiler.ast.AstBuilder.performStackAnalysis(AstBuilder.java:2445)
        //     at com.strobel.decompiler.ast.AstBuilder.build(AstBuilder.java:108)
        //     at com.strobel.decompiler.languages.java.ast.AstMethodBodyBuilder.createMethodBody(AstMethodBodyBuilder.java:211)
        //     at com.strobel.decompiler.languages.java.ast.AstMethodBodyBuilder.createMethodBody(AstMethodBodyBuilder.java:99)
        //     at com.strobel.decompiler.languages.java.ast.AstBuilder.createMethodBody(AstBuilder.java:782)
        //     at com.strobel.decompiler.languages.java.ast.AstBuilder.createMethod(AstBuilder.java:675)
        //     at com.strobel.decompiler.languages.java.ast.AstBuilder.addTypeMembers(AstBuilder.java:552)
        //     at com.strobel.decompiler.languages.java.ast.AstBuilder.createTypeCore(AstBuilder.java:519)
        //     at com.strobel.decompiler.languages.java.ast.AstBuilder.createTypeNoCache(AstBuilder.java:161)
        //     at com.strobel.decompiler.languages.java.ast.AstBuilder.createType(AstBuilder.java:150)
        //     at com.strobel.decompiler.languages.java.ast.AstBuilder.addType(AstBuilder.java:125)
        //     at com.strobel.decompiler.languages.java.JavaLanguage.buildAst(JavaLanguage.java:71)
        //     at com.strobel.decompiler.languages.java.JavaLanguage.decompileType(JavaLanguage.java:59)
        //     at com.strobel.decompiler.DecompilerDriver.decompileType(DecompilerDriver.java:330)
        //     at com.strobel.decompiler.DecompilerDriver.decompileJar(DecompilerDriver.java:251)
        //     at com.strobel.decompiler.DecompilerDriver.main(DecompilerDriver.java:126)
        // 
        throw new IllegalStateException("An error occurred while decompiling this method.");
    }
    
    public synchronized boolean getBGGreetsP() {
        return this.bGGreetsP;
    }
    
    public synchronized boolean getbGGreetsP() {
        return this.bGGreetsP;
    }
    
    public void setBGGreetsP(final boolean p0) {
        // 
        // This method could not be decompiled.
        // 
        // Original Bytecode:
        // 
        //     3: aload_3        
        //     4: monitorexit    
        //     5: athrow         
        //     6: aload_0        
        //     7: dup            
        //     8: astore_3       
        //     9: monitorenter   
        //    10: aload_0        
        //    11: getfield        facade/characters/wmedef/PostBeatMixinInfoWME.bGGreetsP:Z
        //    14: istore_2       
        //    15: aload_0        
        //    16: iload_1        
        //    17: putfield        facade/characters/wmedef/PostBeatMixinInfoWME.bGGreetsP:Z
        //    20: aload_3        
        //    21: monitorexit    
        //    22: aload_0        
        //    23: getfield        facade/characters/wmedef/PostBeatMixinInfoWME.__support:Ljava/beans/PropertyChangeSupport;
        //    26: ldc             "bGGreetsP"
        //    28: iload_2        
        //    29: iload_1        
        //    30: invokevirtual   java/beans/PropertyChangeSupport.firePropertyChange:(Ljava/lang/String;ZZ)V
        //    33: return         
        //    Exceptions:
        //  Try           Handler
        //  Start  End    Start  End    Type
        //  -----  -----  -----  -----  ----
        //  3      5      3      6      Any
        //  10     22     3      6      Any
        // 
        // The error that occurred was:
        // 
        // java.util.ConcurrentModificationException
        //     at java.util.ArrayList$Itr.checkForComodification(Unknown Source)
        //     at java.util.ArrayList$Itr.next(Unknown Source)
        //     at com.strobel.decompiler.ast.AstBuilder.convertLocalVariables(AstBuilder.java:2863)
        //     at com.strobel.decompiler.ast.AstBuilder.performStackAnalysis(AstBuilder.java:2445)
        //     at com.strobel.decompiler.ast.AstBuilder.build(AstBuilder.java:108)
        //     at com.strobel.decompiler.languages.java.ast.AstMethodBodyBuilder.createMethodBody(AstMethodBodyBuilder.java:211)
        //     at com.strobel.decompiler.languages.java.ast.AstMethodBodyBuilder.createMethodBody(AstMethodBodyBuilder.java:99)
        //     at com.strobel.decompiler.languages.java.ast.AstBuilder.createMethodBody(AstBuilder.java:782)
        //     at com.strobel.decompiler.languages.java.ast.AstBuilder.createMethod(AstBuilder.java:675)
        //     at com.strobel.decompiler.languages.java.ast.AstBuilder.addTypeMembers(AstBuilder.java:552)
        //     at com.strobel.decompiler.languages.java.ast.AstBuilder.createTypeCore(AstBuilder.java:519)
        //     at com.strobel.decompiler.languages.java.ast.AstBuilder.createTypeNoCache(AstBuilder.java:161)
        //     at com.strobel.decompiler.languages.java.ast.AstBuilder.createType(AstBuilder.java:150)
        //     at com.strobel.decompiler.languages.java.ast.AstBuilder.addType(AstBuilder.java:125)
        //     at com.strobel.decompiler.languages.java.JavaLanguage.buildAst(JavaLanguage.java:71)
        //     at com.strobel.decompiler.languages.java.JavaLanguage.decompileType(JavaLanguage.java:59)
        //     at com.strobel.decompiler.DecompilerDriver.decompileType(DecompilerDriver.java:330)
        //     at com.strobel.decompiler.DecompilerDriver.decompileJar(DecompilerDriver.java:251)
        //     at com.strobel.decompiler.DecompilerDriver.main(DecompilerDriver.java:126)
        // 
        throw new IllegalStateException("An error occurred while decompiling this method.");
    }
    
    public synchronized boolean getBAA_decorating_txnIn() {
        return this.bAA_decorating_txnIn;
    }
    
    public synchronized boolean getbAA_decorating_txnIn() {
        return this.bAA_decorating_txnIn;
    }
    
    public void setBAA_decorating_txnIn(final boolean p0) {
        // 
        // This method could not be decompiled.
        // 
        // Original Bytecode:
        // 
        //     3: aload_3        
        //     4: monitorexit    
        //     5: athrow         
        //     6: aload_0        
        //     7: dup            
        //     8: astore_3       
        //     9: monitorenter   
        //    10: aload_0        
        //    11: getfield        facade/characters/wmedef/PostBeatMixinInfoWME.bAA_decorating_txnIn:Z
        //    14: istore_2       
        //    15: aload_0        
        //    16: iload_1        
        //    17: putfield        facade/characters/wmedef/PostBeatMixinInfoWME.bAA_decorating_txnIn:Z
        //    20: aload_3        
        //    21: monitorexit    
        //    22: aload_0        
        //    23: getfield        facade/characters/wmedef/PostBeatMixinInfoWME.__support:Ljava/beans/PropertyChangeSupport;
        //    26: ldc             "bAA_decorating_txnIn"
        //    28: iload_2        
        //    29: iload_1        
        //    30: invokevirtual   java/beans/PropertyChangeSupport.firePropertyChange:(Ljava/lang/String;ZZ)V
        //    33: return         
        //    Exceptions:
        //  Try           Handler
        //  Start  End    Start  End    Type
        //  -----  -----  -----  -----  ----
        //  3      5      3      6      Any
        //  10     22     3      6      Any
        // 
        // The error that occurred was:
        // 
        // java.util.ConcurrentModificationException
        //     at java.util.ArrayList$Itr.checkForComodification(Unknown Source)
        //     at java.util.ArrayList$Itr.next(Unknown Source)
        //     at com.strobel.decompiler.ast.AstBuilder.convertLocalVariables(AstBuilder.java:2863)
        //     at com.strobel.decompiler.ast.AstBuilder.performStackAnalysis(AstBuilder.java:2445)
        //     at com.strobel.decompiler.ast.AstBuilder.build(AstBuilder.java:108)
        //     at com.strobel.decompiler.languages.java.ast.AstMethodBodyBuilder.createMethodBody(AstMethodBodyBuilder.java:211)
        //     at com.strobel.decompiler.languages.java.ast.AstMethodBodyBuilder.createMethodBody(AstMethodBodyBuilder.java:99)
        //     at com.strobel.decompiler.languages.java.ast.AstBuilder.createMethodBody(AstBuilder.java:782)
        //     at com.strobel.decompiler.languages.java.ast.AstBuilder.createMethod(AstBuilder.java:675)
        //     at com.strobel.decompiler.languages.java.ast.AstBuilder.addTypeMembers(AstBuilder.java:552)
        //     at com.strobel.decompiler.languages.java.ast.AstBuilder.createTypeCore(AstBuilder.java:519)
        //     at com.strobel.decompiler.languages.java.ast.AstBuilder.createTypeNoCache(AstBuilder.java:161)
        //     at com.strobel.decompiler.languages.java.ast.AstBuilder.createType(AstBuilder.java:150)
        //     at com.strobel.decompiler.languages.java.ast.AstBuilder.addType(AstBuilder.java:125)
        //     at com.strobel.decompiler.languages.java.JavaLanguage.buildAst(JavaLanguage.java:71)
        //     at com.strobel.decompiler.languages.java.JavaLanguage.decompileType(JavaLanguage.java:59)
        //     at com.strobel.decompiler.DecompilerDriver.decompileType(DecompilerDriver.java:330)
        //     at com.strobel.decompiler.DecompilerDriver.decompileJar(DecompilerDriver.java:251)
        //     at com.strobel.decompiler.DecompilerDriver.main(DecompilerDriver.java:126)
        // 
        throw new IllegalStateException("An error occurred while decompiling this method.");
    }
    
    public synchronized boolean getBAA_decorating_txnOut() {
        return this.bAA_decorating_txnOut;
    }
    
    public synchronized boolean getbAA_decorating_txnOut() {
        return this.bAA_decorating_txnOut;
    }
    
    public void setBAA_decorating_txnOut(final boolean p0) {
        // 
        // This method could not be decompiled.
        // 
        // Original Bytecode:
        // 
        //     3: aload_3        
        //     4: monitorexit    
        //     5: athrow         
        //     6: aload_0        
        //     7: dup            
        //     8: astore_3       
        //     9: monitorenter   
        //    10: aload_0        
        //    11: getfield        facade/characters/wmedef/PostBeatMixinInfoWME.bAA_decorating_txnOut:Z
        //    14: istore_2       
        //    15: aload_0        
        //    16: iload_1        
        //    17: putfield        facade/characters/wmedef/PostBeatMixinInfoWME.bAA_decorating_txnOut:Z
        //    20: aload_3        
        //    21: monitorexit    
        //    22: aload_0        
        //    23: getfield        facade/characters/wmedef/PostBeatMixinInfoWME.__support:Ljava/beans/PropertyChangeSupport;
        //    26: ldc             "bAA_decorating_txnOut"
        //    28: iload_2        
        //    29: iload_1        
        //    30: invokevirtual   java/beans/PropertyChangeSupport.firePropertyChange:(Ljava/lang/String;ZZ)V
        //    33: return         
        //    Exceptions:
        //  Try           Handler
        //  Start  End    Start  End    Type
        //  -----  -----  -----  -----  ----
        //  3      5      3      6      Any
        //  10     22     3      6      Any
        // 
        // The error that occurred was:
        // 
        // java.util.ConcurrentModificationException
        //     at java.util.ArrayList$Itr.checkForComodification(Unknown Source)
        //     at java.util.ArrayList$Itr.next(Unknown Source)
        //     at com.strobel.decompiler.ast.AstBuilder.convertLocalVariables(AstBuilder.java:2863)
        //     at com.strobel.decompiler.ast.AstBuilder.performStackAnalysis(AstBuilder.java:2445)
        //     at com.strobel.decompiler.ast.AstBuilder.build(AstBuilder.java:108)
        //     at com.strobel.decompiler.languages.java.ast.AstMethodBodyBuilder.createMethodBody(AstMethodBodyBuilder.java:211)
        //     at com.strobel.decompiler.languages.java.ast.AstMethodBodyBuilder.createMethodBody(AstMethodBodyBuilder.java:99)
        //     at com.strobel.decompiler.languages.java.ast.AstBuilder.createMethodBody(AstBuilder.java:782)
        //     at com.strobel.decompiler.languages.java.ast.AstBuilder.createMethod(AstBuilder.java:675)
        //     at com.strobel.decompiler.languages.java.ast.AstBuilder.addTypeMembers(AstBuilder.java:552)
        //     at com.strobel.decompiler.languages.java.ast.AstBuilder.createTypeCore(AstBuilder.java:519)
        //     at com.strobel.decompiler.languages.java.ast.AstBuilder.createTypeNoCache(AstBuilder.java:161)
        //     at com.strobel.decompiler.languages.java.ast.AstBuilder.createType(AstBuilder.java:150)
        //     at com.strobel.decompiler.languages.java.ast.AstBuilder.addType(AstBuilder.java:125)
        //     at com.strobel.decompiler.languages.java.JavaLanguage.buildAst(JavaLanguage.java:71)
        //     at com.strobel.decompiler.languages.java.JavaLanguage.decompileType(JavaLanguage.java:59)
        //     at com.strobel.decompiler.DecompilerDriver.decompileType(DecompilerDriver.java:330)
        //     at com.strobel.decompiler.DecompilerDriver.decompileJar(DecompilerDriver.java:251)
        //     at com.strobel.decompiler.DecompilerDriver.main(DecompilerDriver.java:126)
        // 
        throw new IllegalStateException("An error occurred while decompiling this method.");
    }
    
    public synchronized boolean getBAA_decorating_styleApt() {
        return this.bAA_decorating_styleApt;
    }
    
    public synchronized boolean getbAA_decorating_styleApt() {
        return this.bAA_decorating_styleApt;
    }
    
    public void setBAA_decorating_styleApt(final boolean p0) {
        // 
        // This method could not be decompiled.
        // 
        // Original Bytecode:
        // 
        //     3: aload_3        
        //     4: monitorexit    
        //     5: athrow         
        //     6: aload_0        
        //     7: dup            
        //     8: astore_3       
        //     9: monitorenter   
        //    10: aload_0        
        //    11: getfield        facade/characters/wmedef/PostBeatMixinInfoWME.bAA_decorating_styleApt:Z
        //    14: istore_2       
        //    15: aload_0        
        //    16: iload_1        
        //    17: putfield        facade/characters/wmedef/PostBeatMixinInfoWME.bAA_decorating_styleApt:Z
        //    20: aload_3        
        //    21: monitorexit    
        //    22: aload_0        
        //    23: getfield        facade/characters/wmedef/PostBeatMixinInfoWME.__support:Ljava/beans/PropertyChangeSupport;
        //    26: ldc             "bAA_decorating_styleApt"
        //    28: iload_2        
        //    29: iload_1        
        //    30: invokevirtual   java/beans/PropertyChangeSupport.firePropertyChange:(Ljava/lang/String;ZZ)V
        //    33: return         
        //    Exceptions:
        //  Try           Handler
        //  Start  End    Start  End    Type
        //  -----  -----  -----  -----  ----
        //  3      5      3      6      Any
        //  10     22     3      6      Any
        // 
        // The error that occurred was:
        // 
        // java.util.ConcurrentModificationException
        //     at java.util.ArrayList$Itr.checkForComodification(Unknown Source)
        //     at java.util.ArrayList$Itr.next(Unknown Source)
        //     at com.strobel.decompiler.ast.AstBuilder.convertLocalVariables(AstBuilder.java:2863)
        //     at com.strobel.decompiler.ast.AstBuilder.performStackAnalysis(AstBuilder.java:2445)
        //     at com.strobel.decompiler.ast.AstBuilder.build(AstBuilder.java:108)
        //     at com.strobel.decompiler.languages.java.ast.AstMethodBodyBuilder.createMethodBody(AstMethodBodyBuilder.java:211)
        //     at com.strobel.decompiler.languages.java.ast.AstMethodBodyBuilder.createMethodBody(AstMethodBodyBuilder.java:99)
        //     at com.strobel.decompiler.languages.java.ast.AstBuilder.createMethodBody(AstBuilder.java:782)
        //     at com.strobel.decompiler.languages.java.ast.AstBuilder.createMethod(AstBuilder.java:675)
        //     at com.strobel.decompiler.languages.java.ast.AstBuilder.addTypeMembers(AstBuilder.java:552)
        //     at com.strobel.decompiler.languages.java.ast.AstBuilder.createTypeCore(AstBuilder.java:519)
        //     at com.strobel.decompiler.languages.java.ast.AstBuilder.createTypeNoCache(AstBuilder.java:161)
        //     at com.strobel.decompiler.languages.java.ast.AstBuilder.createType(AstBuilder.java:150)
        //     at com.strobel.decompiler.languages.java.ast.AstBuilder.addType(AstBuilder.java:125)
        //     at com.strobel.decompiler.languages.java.JavaLanguage.buildAst(JavaLanguage.java:71)
        //     at com.strobel.decompiler.languages.java.JavaLanguage.decompileType(JavaLanguage.java:59)
        //     at com.strobel.decompiler.DecompilerDriver.decompileType(DecompilerDriver.java:330)
        //     at com.strobel.decompiler.DecompilerDriver.decompileJar(DecompilerDriver.java:251)
        //     at com.strobel.decompiler.DecompilerDriver.main(DecompilerDriver.java:126)
        // 
        throw new IllegalStateException("An error occurred while decompiling this method.");
    }
    
    public synchronized boolean getBAA_decorating_couch() {
        return this.bAA_decorating_couch;
    }
    
    public synchronized boolean getbAA_decorating_couch() {
        return this.bAA_decorating_couch;
    }
    
    public void setBAA_decorating_couch(final boolean p0) {
        // 
        // This method could not be decompiled.
        // 
        // Original Bytecode:
        // 
        //     3: aload_3        
        //     4: monitorexit    
        //     5: athrow         
        //     6: aload_0        
        //     7: dup            
        //     8: astore_3       
        //     9: monitorenter   
        //    10: aload_0        
        //    11: getfield        facade/characters/wmedef/PostBeatMixinInfoWME.bAA_decorating_couch:Z
        //    14: istore_2       
        //    15: aload_0        
        //    16: iload_1        
        //    17: putfield        facade/characters/wmedef/PostBeatMixinInfoWME.bAA_decorating_couch:Z
        //    20: aload_3        
        //    21: monitorexit    
        //    22: aload_0        
        //    23: getfield        facade/characters/wmedef/PostBeatMixinInfoWME.__support:Ljava/beans/PropertyChangeSupport;
        //    26: ldc             "bAA_decorating_couch"
        //    28: iload_2        
        //    29: iload_1        
        //    30: invokevirtual   java/beans/PropertyChangeSupport.firePropertyChange:(Ljava/lang/String;ZZ)V
        //    33: return         
        //    Exceptions:
        //  Try           Handler
        //  Start  End    Start  End    Type
        //  -----  -----  -----  -----  ----
        //  3      5      3      6      Any
        //  10     22     3      6      Any
        // 
        // The error that occurred was:
        // 
        // java.util.ConcurrentModificationException
        //     at java.util.ArrayList$Itr.checkForComodification(Unknown Source)
        //     at java.util.ArrayList$Itr.next(Unknown Source)
        //     at com.strobel.decompiler.ast.AstBuilder.convertLocalVariables(AstBuilder.java:2863)
        //     at com.strobel.decompiler.ast.AstBuilder.performStackAnalysis(AstBuilder.java:2445)
        //     at com.strobel.decompiler.ast.AstBuilder.build(AstBuilder.java:108)
        //     at com.strobel.decompiler.languages.java.ast.AstMethodBodyBuilder.createMethodBody(AstMethodBodyBuilder.java:211)
        //     at com.strobel.decompiler.languages.java.ast.AstMethodBodyBuilder.createMethodBody(AstMethodBodyBuilder.java:99)
        //     at com.strobel.decompiler.languages.java.ast.AstBuilder.createMethodBody(AstBuilder.java:782)
        //     at com.strobel.decompiler.languages.java.ast.AstBuilder.createMethod(AstBuilder.java:675)
        //     at com.strobel.decompiler.languages.java.ast.AstBuilder.addTypeMembers(AstBuilder.java:552)
        //     at com.strobel.decompiler.languages.java.ast.AstBuilder.createTypeCore(AstBuilder.java:519)
        //     at com.strobel.decompiler.languages.java.ast.AstBuilder.createTypeNoCache(AstBuilder.java:161)
        //     at com.strobel.decompiler.languages.java.ast.AstBuilder.createType(AstBuilder.java:150)
        //     at com.strobel.decompiler.languages.java.ast.AstBuilder.addType(AstBuilder.java:125)
        //     at com.strobel.decompiler.languages.java.JavaLanguage.buildAst(JavaLanguage.java:71)
        //     at com.strobel.decompiler.languages.java.JavaLanguage.decompileType(JavaLanguage.java:59)
        //     at com.strobel.decompiler.DecompilerDriver.decompileType(DecompilerDriver.java:330)
        //     at com.strobel.decompiler.DecompilerDriver.decompileJar(DecompilerDriver.java:251)
        //     at com.strobel.decompiler.DecompilerDriver.main(DecompilerDriver.java:126)
        // 
        throw new IllegalStateException("An error occurred while decompiling this method.");
    }
    
    public synchronized boolean getBAA_decorating_armoire() {
        return this.bAA_decorating_armoire;
    }
    
    public synchronized boolean getbAA_decorating_armoire() {
        return this.bAA_decorating_armoire;
    }
    
    public void setBAA_decorating_armoire(final boolean p0) {
        // 
        // This method could not be decompiled.
        // 
        // Original Bytecode:
        // 
        //     3: aload_3        
        //     4: monitorexit    
        //     5: athrow         
        //     6: aload_0        
        //     7: dup            
        //     8: astore_3       
        //     9: monitorenter   
        //    10: aload_0        
        //    11: getfield        facade/characters/wmedef/PostBeatMixinInfoWME.bAA_decorating_armoire:Z
        //    14: istore_2       
        //    15: aload_0        
        //    16: iload_1        
        //    17: putfield        facade/characters/wmedef/PostBeatMixinInfoWME.bAA_decorating_armoire:Z
        //    20: aload_3        
        //    21: monitorexit    
        //    22: aload_0        
        //    23: getfield        facade/characters/wmedef/PostBeatMixinInfoWME.__support:Ljava/beans/PropertyChangeSupport;
        //    26: ldc             "bAA_decorating_armoire"
        //    28: iload_2        
        //    29: iload_1        
        //    30: invokevirtual   java/beans/PropertyChangeSupport.firePropertyChange:(Ljava/lang/String;ZZ)V
        //    33: return         
        //    Exceptions:
        //  Try           Handler
        //  Start  End    Start  End    Type
        //  -----  -----  -----  -----  ----
        //  3      5      3      6      Any
        //  10     22     3      6      Any
        // 
        // The error that occurred was:
        // 
        // java.util.ConcurrentModificationException
        //     at java.util.ArrayList$Itr.checkForComodification(Unknown Source)
        //     at java.util.ArrayList$Itr.next(Unknown Source)
        //     at com.strobel.decompiler.ast.AstBuilder.convertLocalVariables(AstBuilder.java:2863)
        //     at com.strobel.decompiler.ast.AstBuilder.performStackAnalysis(AstBuilder.java:2445)
        //     at com.strobel.decompiler.ast.AstBuilder.build(AstBuilder.java:108)
        //     at com.strobel.decompiler.languages.java.ast.AstMethodBodyBuilder.createMethodBody(AstMethodBodyBuilder.java:211)
        //     at com.strobel.decompiler.languages.java.ast.AstMethodBodyBuilder.createMethodBody(AstMethodBodyBuilder.java:99)
        //     at com.strobel.decompiler.languages.java.ast.AstBuilder.createMethodBody(AstBuilder.java:782)
        //     at com.strobel.decompiler.languages.java.ast.AstBuilder.createMethod(AstBuilder.java:675)
        //     at com.strobel.decompiler.languages.java.ast.AstBuilder.addTypeMembers(AstBuilder.java:552)
        //     at com.strobel.decompiler.languages.java.ast.AstBuilder.createTypeCore(AstBuilder.java:519)
        //     at com.strobel.decompiler.languages.java.ast.AstBuilder.createTypeNoCache(AstBuilder.java:161)
        //     at com.strobel.decompiler.languages.java.ast.AstBuilder.createType(AstBuilder.java:150)
        //     at com.strobel.decompiler.languages.java.ast.AstBuilder.addType(AstBuilder.java:125)
        //     at com.strobel.decompiler.languages.java.JavaLanguage.buildAst(JavaLanguage.java:71)
        //     at com.strobel.decompiler.languages.java.JavaLanguage.decompileType(JavaLanguage.java:59)
        //     at com.strobel.decompiler.DecompilerDriver.decompileType(DecompilerDriver.java:330)
        //     at com.strobel.decompiler.DecompilerDriver.decompileJar(DecompilerDriver.java:251)
        //     at com.strobel.decompiler.DecompilerDriver.main(DecompilerDriver.java:126)
        // 
        throw new IllegalStateException("An error occurred while decompiling this method.");
    }
    
    public synchronized boolean getBAA_decorating_trinkets() {
        return this.bAA_decorating_trinkets;
    }
    
    public synchronized boolean getbAA_decorating_trinkets() {
        return this.bAA_decorating_trinkets;
    }
    
    public void setBAA_decorating_trinkets(final boolean p0) {
        // 
        // This method could not be decompiled.
        // 
        // Original Bytecode:
        // 
        //     3: aload_3        
        //     4: monitorexit    
        //     5: athrow         
        //     6: aload_0        
        //     7: dup            
        //     8: astore_3       
        //     9: monitorenter   
        //    10: aload_0        
        //    11: getfield        facade/characters/wmedef/PostBeatMixinInfoWME.bAA_decorating_trinkets:Z
        //    14: istore_2       
        //    15: aload_0        
        //    16: iload_1        
        //    17: putfield        facade/characters/wmedef/PostBeatMixinInfoWME.bAA_decorating_trinkets:Z
        //    20: aload_3        
        //    21: monitorexit    
        //    22: aload_0        
        //    23: getfield        facade/characters/wmedef/PostBeatMixinInfoWME.__support:Ljava/beans/PropertyChangeSupport;
        //    26: ldc             "bAA_decorating_trinkets"
        //    28: iload_2        
        //    29: iload_1        
        //    30: invokevirtual   java/beans/PropertyChangeSupport.firePropertyChange:(Ljava/lang/String;ZZ)V
        //    33: return         
        //    Exceptions:
        //  Try           Handler
        //  Start  End    Start  End    Type
        //  -----  -----  -----  -----  ----
        //  3      5      3      6      Any
        //  10     22     3      6      Any
        // 
        // The error that occurred was:
        // 
        // java.util.ConcurrentModificationException
        //     at java.util.ArrayList$Itr.checkForComodification(Unknown Source)
        //     at java.util.ArrayList$Itr.next(Unknown Source)
        //     at com.strobel.decompiler.ast.AstBuilder.convertLocalVariables(AstBuilder.java:2863)
        //     at com.strobel.decompiler.ast.AstBuilder.performStackAnalysis(AstBuilder.java:2445)
        //     at com.strobel.decompiler.ast.AstBuilder.build(AstBuilder.java:108)
        //     at com.strobel.decompiler.languages.java.ast.AstMethodBodyBuilder.createMethodBody(AstMethodBodyBuilder.java:211)
        //     at com.strobel.decompiler.languages.java.ast.AstMethodBodyBuilder.createMethodBody(AstMethodBodyBuilder.java:99)
        //     at com.strobel.decompiler.languages.java.ast.AstBuilder.createMethodBody(AstBuilder.java:782)
        //     at com.strobel.decompiler.languages.java.ast.AstBuilder.createMethod(AstBuilder.java:675)
        //     at com.strobel.decompiler.languages.java.ast.AstBuilder.addTypeMembers(AstBuilder.java:552)
        //     at com.strobel.decompiler.languages.java.ast.AstBuilder.createTypeCore(AstBuilder.java:519)
        //     at com.strobel.decompiler.languages.java.ast.AstBuilder.createTypeNoCache(AstBuilder.java:161)
        //     at com.strobel.decompiler.languages.java.ast.AstBuilder.createType(AstBuilder.java:150)
        //     at com.strobel.decompiler.languages.java.ast.AstBuilder.addType(AstBuilder.java:125)
        //     at com.strobel.decompiler.languages.java.JavaLanguage.buildAst(JavaLanguage.java:71)
        //     at com.strobel.decompiler.languages.java.JavaLanguage.decompileType(JavaLanguage.java:59)
        //     at com.strobel.decompiler.DecompilerDriver.decompileType(DecompilerDriver.java:330)
        //     at com.strobel.decompiler.DecompilerDriver.decompileJar(DecompilerDriver.java:251)
        //     at com.strobel.decompiler.DecompilerDriver.main(DecompilerDriver.java:126)
        // 
        throw new IllegalStateException("An error occurred while decompiling this method.");
    }
    
    public synchronized boolean getBAA_decorating_paintings() {
        return this.bAA_decorating_paintings;
    }
    
    public synchronized boolean getbAA_decorating_paintings() {
        return this.bAA_decorating_paintings;
    }
    
    public void setBAA_decorating_paintings(final boolean p0) {
        // 
        // This method could not be decompiled.
        // 
        // Original Bytecode:
        // 
        //     3: aload_3        
        //     4: monitorexit    
        //     5: athrow         
        //     6: aload_0        
        //     7: dup            
        //     8: astore_3       
        //     9: monitorenter   
        //    10: aload_0        
        //    11: getfield        facade/characters/wmedef/PostBeatMixinInfoWME.bAA_decorating_paintings:Z
        //    14: istore_2       
        //    15: aload_0        
        //    16: iload_1        
        //    17: putfield        facade/characters/wmedef/PostBeatMixinInfoWME.bAA_decorating_paintings:Z
        //    20: aload_3        
        //    21: monitorexit    
        //    22: aload_0        
        //    23: getfield        facade/characters/wmedef/PostBeatMixinInfoWME.__support:Ljava/beans/PropertyChangeSupport;
        //    26: ldc             "bAA_decorating_paintings"
        //    28: iload_2        
        //    29: iload_1        
        //    30: invokevirtual   java/beans/PropertyChangeSupport.firePropertyChange:(Ljava/lang/String;ZZ)V
        //    33: return         
        //    Exceptions:
        //  Try           Handler
        //  Start  End    Start  End    Type
        //  -----  -----  -----  -----  ----
        //  3      5      3      6      Any
        //  10     22     3      6      Any
        // 
        // The error that occurred was:
        // 
        // java.util.ConcurrentModificationException
        //     at java.util.ArrayList$Itr.checkForComodification(Unknown Source)
        //     at java.util.ArrayList$Itr.next(Unknown Source)
        //     at com.strobel.decompiler.ast.AstBuilder.convertLocalVariables(AstBuilder.java:2863)
        //     at com.strobel.decompiler.ast.AstBuilder.performStackAnalysis(AstBuilder.java:2445)
        //     at com.strobel.decompiler.ast.AstBuilder.build(AstBuilder.java:108)
        //     at com.strobel.decompiler.languages.java.ast.AstMethodBodyBuilder.createMethodBody(AstMethodBodyBuilder.java:211)
        //     at com.strobel.decompiler.languages.java.ast.AstMethodBodyBuilder.createMethodBody(AstMethodBodyBuilder.java:99)
        //     at com.strobel.decompiler.languages.java.ast.AstBuilder.createMethodBody(AstBuilder.java:782)
        //     at com.strobel.decompiler.languages.java.ast.AstBuilder.createMethod(AstBuilder.java:675)
        //     at com.strobel.decompiler.languages.java.ast.AstBuilder.addTypeMembers(AstBuilder.java:552)
        //     at com.strobel.decompiler.languages.java.ast.AstBuilder.createTypeCore(AstBuilder.java:519)
        //     at com.strobel.decompiler.languages.java.ast.AstBuilder.createTypeNoCache(AstBuilder.java:161)
        //     at com.strobel.decompiler.languages.java.ast.AstBuilder.createType(AstBuilder.java:150)
        //     at com.strobel.decompiler.languages.java.ast.AstBuilder.addType(AstBuilder.java:125)
        //     at com.strobel.decompiler.languages.java.JavaLanguage.buildAst(JavaLanguage.java:71)
        //     at com.strobel.decompiler.languages.java.JavaLanguage.decompileType(JavaLanguage.java:59)
        //     at com.strobel.decompiler.DecompilerDriver.decompileType(DecompilerDriver.java:330)
        //     at com.strobel.decompiler.DecompilerDriver.decompileJar(DecompilerDriver.java:251)
        //     at com.strobel.decompiler.DecompilerDriver.main(DecompilerDriver.java:126)
        // 
        throw new IllegalStateException("An error occurred while decompiling this method.");
    }
    
    public synchronized boolean getBAA_decorating_weddingPicture() {
        return this.bAA_decorating_weddingPicture;
    }
    
    public synchronized boolean getbAA_decorating_weddingPicture() {
        return this.bAA_decorating_weddingPicture;
    }
    
    public void setBAA_decorating_weddingPicture(final boolean p0) {
        // 
        // This method could not be decompiled.
        // 
        // Original Bytecode:
        // 
        //     3: aload_3        
        //     4: monitorexit    
        //     5: athrow         
        //     6: aload_0        
        //     7: dup            
        //     8: astore_3       
        //     9: monitorenter   
        //    10: aload_0        
        //    11: getfield        facade/characters/wmedef/PostBeatMixinInfoWME.bAA_decorating_weddingPicture:Z
        //    14: istore_2       
        //    15: aload_0        
        //    16: iload_1        
        //    17: putfield        facade/characters/wmedef/PostBeatMixinInfoWME.bAA_decorating_weddingPicture:Z
        //    20: aload_3        
        //    21: monitorexit    
        //    22: aload_0        
        //    23: getfield        facade/characters/wmedef/PostBeatMixinInfoWME.__support:Ljava/beans/PropertyChangeSupport;
        //    26: ldc             "bAA_decorating_weddingPicture"
        //    28: iload_2        
        //    29: iload_1        
        //    30: invokevirtual   java/beans/PropertyChangeSupport.firePropertyChange:(Ljava/lang/String;ZZ)V
        //    33: return         
        //    Exceptions:
        //  Try           Handler
        //  Start  End    Start  End    Type
        //  -----  -----  -----  -----  ----
        //  3      5      3      6      Any
        //  10     22     3      6      Any
        // 
        // The error that occurred was:
        // 
        // java.util.ConcurrentModificationException
        //     at java.util.ArrayList$Itr.checkForComodification(Unknown Source)
        //     at java.util.ArrayList$Itr.next(Unknown Source)
        //     at com.strobel.decompiler.ast.AstBuilder.convertLocalVariables(AstBuilder.java:2863)
        //     at com.strobel.decompiler.ast.AstBuilder.performStackAnalysis(AstBuilder.java:2445)
        //     at com.strobel.decompiler.ast.AstBuilder.build(AstBuilder.java:108)
        //     at com.strobel.decompiler.languages.java.ast.AstMethodBodyBuilder.createMethodBody(AstMethodBodyBuilder.java:211)
        //     at com.strobel.decompiler.languages.java.ast.AstMethodBodyBuilder.createMethodBody(AstMethodBodyBuilder.java:99)
        //     at com.strobel.decompiler.languages.java.ast.AstBuilder.createMethodBody(AstBuilder.java:782)
        //     at com.strobel.decompiler.languages.java.ast.AstBuilder.createMethod(AstBuilder.java:675)
        //     at com.strobel.decompiler.languages.java.ast.AstBuilder.addTypeMembers(AstBuilder.java:552)
        //     at com.strobel.decompiler.languages.java.ast.AstBuilder.createTypeCore(AstBuilder.java:519)
        //     at com.strobel.decompiler.languages.java.ast.AstBuilder.createTypeNoCache(AstBuilder.java:161)
        //     at com.strobel.decompiler.languages.java.ast.AstBuilder.createType(AstBuilder.java:150)
        //     at com.strobel.decompiler.languages.java.ast.AstBuilder.addType(AstBuilder.java:125)
        //     at com.strobel.decompiler.languages.java.JavaLanguage.buildAst(JavaLanguage.java:71)
        //     at com.strobel.decompiler.languages.java.JavaLanguage.decompileType(JavaLanguage.java:59)
        //     at com.strobel.decompiler.DecompilerDriver.decompileType(DecompilerDriver.java:330)
        //     at com.strobel.decompiler.DecompilerDriver.decompileJar(DecompilerDriver.java:251)
        //     at com.strobel.decompiler.DecompilerDriver.main(DecompilerDriver.java:126)
        // 
        throw new IllegalStateException("An error occurred while decompiling this method.");
    }
    
    public synchronized boolean getBAA_decorating_view() {
        return this.bAA_decorating_view;
    }
    
    public synchronized boolean getbAA_decorating_view() {
        return this.bAA_decorating_view;
    }
    
    public void setBAA_decorating_view(final boolean p0) {
        // 
        // This method could not be decompiled.
        // 
        // Original Bytecode:
        // 
        //     3: aload_3        
        //     4: monitorexit    
        //     5: athrow         
        //     6: aload_0        
        //     7: dup            
        //     8: astore_3       
        //     9: monitorenter   
        //    10: aload_0        
        //    11: getfield        facade/characters/wmedef/PostBeatMixinInfoWME.bAA_decorating_view:Z
        //    14: istore_2       
        //    15: aload_0        
        //    16: iload_1        
        //    17: putfield        facade/characters/wmedef/PostBeatMixinInfoWME.bAA_decorating_view:Z
        //    20: aload_3        
        //    21: monitorexit    
        //    22: aload_0        
        //    23: getfield        facade/characters/wmedef/PostBeatMixinInfoWME.__support:Ljava/beans/PropertyChangeSupport;
        //    26: ldc             "bAA_decorating_view"
        //    28: iload_2        
        //    29: iload_1        
        //    30: invokevirtual   java/beans/PropertyChangeSupport.firePropertyChange:(Ljava/lang/String;ZZ)V
        //    33: return         
        //    Exceptions:
        //  Try           Handler
        //  Start  End    Start  End    Type
        //  -----  -----  -----  -----  ----
        //  3      5      3      6      Any
        //  10     22     3      6      Any
        // 
        // The error that occurred was:
        // 
        // java.util.ConcurrentModificationException
        //     at java.util.ArrayList$Itr.checkForComodification(Unknown Source)
        //     at java.util.ArrayList$Itr.next(Unknown Source)
        //     at com.strobel.decompiler.ast.AstBuilder.convertLocalVariables(AstBuilder.java:2863)
        //     at com.strobel.decompiler.ast.AstBuilder.performStackAnalysis(AstBuilder.java:2445)
        //     at com.strobel.decompiler.ast.AstBuilder.build(AstBuilder.java:108)
        //     at com.strobel.decompiler.languages.java.ast.AstMethodBodyBuilder.createMethodBody(AstMethodBodyBuilder.java:211)
        //     at com.strobel.decompiler.languages.java.ast.AstMethodBodyBuilder.createMethodBody(AstMethodBodyBuilder.java:99)
        //     at com.strobel.decompiler.languages.java.ast.AstBuilder.createMethodBody(AstBuilder.java:782)
        //     at com.strobel.decompiler.languages.java.ast.AstBuilder.createMethod(AstBuilder.java:675)
        //     at com.strobel.decompiler.languages.java.ast.AstBuilder.addTypeMembers(AstBuilder.java:552)
        //     at com.strobel.decompiler.languages.java.ast.AstBuilder.createTypeCore(AstBuilder.java:519)
        //     at com.strobel.decompiler.languages.java.ast.AstBuilder.createTypeNoCache(AstBuilder.java:161)
        //     at com.strobel.decompiler.languages.java.ast.AstBuilder.createType(AstBuilder.java:150)
        //     at com.strobel.decompiler.languages.java.ast.AstBuilder.addType(AstBuilder.java:125)
        //     at com.strobel.decompiler.languages.java.JavaLanguage.buildAst(JavaLanguage.java:71)
        //     at com.strobel.decompiler.languages.java.JavaLanguage.decompileType(JavaLanguage.java:59)
        //     at com.strobel.decompiler.DecompilerDriver.decompileType(DecompilerDriver.java:330)
        //     at com.strobel.decompiler.DecompilerDriver.decompileJar(DecompilerDriver.java:251)
        //     at com.strobel.decompiler.DecompilerDriver.main(DecompilerDriver.java:126)
        // 
        throw new IllegalStateException("An error occurred while decompiling this method.");
    }
    
    public synchronized boolean getBAA_decorating_sideTable() {
        return this.bAA_decorating_sideTable;
    }
    
    public synchronized boolean getbAA_decorating_sideTable() {
        return this.bAA_decorating_sideTable;
    }
    
    public void setBAA_decorating_sideTable(final boolean p0) {
        // 
        // This method could not be decompiled.
        // 
        // Original Bytecode:
        // 
        //     3: aload_3        
        //     4: monitorexit    
        //     5: athrow         
        //     6: aload_0        
        //     7: dup            
        //     8: astore_3       
        //     9: monitorenter   
        //    10: aload_0        
        //    11: getfield        facade/characters/wmedef/PostBeatMixinInfoWME.bAA_decorating_sideTable:Z
        //    14: istore_2       
        //    15: aload_0        
        //    16: iload_1        
        //    17: putfield        facade/characters/wmedef/PostBeatMixinInfoWME.bAA_decorating_sideTable:Z
        //    20: aload_3        
        //    21: monitorexit    
        //    22: aload_0        
        //    23: getfield        facade/characters/wmedef/PostBeatMixinInfoWME.__support:Ljava/beans/PropertyChangeSupport;
        //    26: ldc             "bAA_decorating_sideTable"
        //    28: iload_2        
        //    29: iload_1        
        //    30: invokevirtual   java/beans/PropertyChangeSupport.firePropertyChange:(Ljava/lang/String;ZZ)V
        //    33: return         
        //    Exceptions:
        //  Try           Handler
        //  Start  End    Start  End    Type
        //  -----  -----  -----  -----  ----
        //  3      5      3      6      Any
        //  10     22     3      6      Any
        // 
        // The error that occurred was:
        // 
        // java.util.ConcurrentModificationException
        //     at java.util.ArrayList$Itr.checkForComodification(Unknown Source)
        //     at java.util.ArrayList$Itr.next(Unknown Source)
        //     at com.strobel.decompiler.ast.AstBuilder.convertLocalVariables(AstBuilder.java:2863)
        //     at com.strobel.decompiler.ast.AstBuilder.performStackAnalysis(AstBuilder.java:2445)
        //     at com.strobel.decompiler.ast.AstBuilder.build(AstBuilder.java:108)
        //     at com.strobel.decompiler.languages.java.ast.AstMethodBodyBuilder.createMethodBody(AstMethodBodyBuilder.java:211)
        //     at com.strobel.decompiler.languages.java.ast.AstMethodBodyBuilder.createMethodBody(AstMethodBodyBuilder.java:99)
        //     at com.strobel.decompiler.languages.java.ast.AstBuilder.createMethodBody(AstBuilder.java:782)
        //     at com.strobel.decompiler.languages.java.ast.AstBuilder.createMethod(AstBuilder.java:675)
        //     at com.strobel.decompiler.languages.java.ast.AstBuilder.addTypeMembers(AstBuilder.java:552)
        //     at com.strobel.decompiler.languages.java.ast.AstBuilder.createTypeCore(AstBuilder.java:519)
        //     at com.strobel.decompiler.languages.java.ast.AstBuilder.createTypeNoCache(AstBuilder.java:161)
        //     at com.strobel.decompiler.languages.java.ast.AstBuilder.createType(AstBuilder.java:150)
        //     at com.strobel.decompiler.languages.java.ast.AstBuilder.addType(AstBuilder.java:125)
        //     at com.strobel.decompiler.languages.java.JavaLanguage.buildAst(JavaLanguage.java:71)
        //     at com.strobel.decompiler.languages.java.JavaLanguage.decompileType(JavaLanguage.java:59)
        //     at com.strobel.decompiler.DecompilerDriver.decompileType(DecompilerDriver.java:330)
        //     at com.strobel.decompiler.DecompilerDriver.decompileJar(DecompilerDriver.java:251)
        //     at com.strobel.decompiler.DecompilerDriver.main(DecompilerDriver.java:126)
        // 
        throw new IllegalStateException("An error occurred while decompiling this method.");
    }
    
    public synchronized boolean getBAA_decorating_rug() {
        return this.bAA_decorating_rug;
    }
    
    public synchronized boolean getbAA_decorating_rug() {
        return this.bAA_decorating_rug;
    }
    
    public void setBAA_decorating_rug(final boolean p0) {
        // 
        // This method could not be decompiled.
        // 
        // Original Bytecode:
        // 
        //     3: aload_3        
        //     4: monitorexit    
        //     5: athrow         
        //     6: aload_0        
        //     7: dup            
        //     8: astore_3       
        //     9: monitorenter   
        //    10: aload_0        
        //    11: getfield        facade/characters/wmedef/PostBeatMixinInfoWME.bAA_decorating_rug:Z
        //    14: istore_2       
        //    15: aload_0        
        //    16: iload_1        
        //    17: putfield        facade/characters/wmedef/PostBeatMixinInfoWME.bAA_decorating_rug:Z
        //    20: aload_3        
        //    21: monitorexit    
        //    22: aload_0        
        //    23: getfield        facade/characters/wmedef/PostBeatMixinInfoWME.__support:Ljava/beans/PropertyChangeSupport;
        //    26: ldc             "bAA_decorating_rug"
        //    28: iload_2        
        //    29: iload_1        
        //    30: invokevirtual   java/beans/PropertyChangeSupport.firePropertyChange:(Ljava/lang/String;ZZ)V
        //    33: return         
        //    Exceptions:
        //  Try           Handler
        //  Start  End    Start  End    Type
        //  -----  -----  -----  -----  ----
        //  3      5      3      6      Any
        //  10     22     3      6      Any
        // 
        // The error that occurred was:
        // 
        // java.util.ConcurrentModificationException
        //     at java.util.ArrayList$Itr.checkForComodification(Unknown Source)
        //     at java.util.ArrayList$Itr.next(Unknown Source)
        //     at com.strobel.decompiler.ast.AstBuilder.convertLocalVariables(AstBuilder.java:2863)
        //     at com.strobel.decompiler.ast.AstBuilder.performStackAnalysis(AstBuilder.java:2445)
        //     at com.strobel.decompiler.ast.AstBuilder.build(AstBuilder.java:108)
        //     at com.strobel.decompiler.languages.java.ast.AstMethodBodyBuilder.createMethodBody(AstMethodBodyBuilder.java:211)
        //     at com.strobel.decompiler.languages.java.ast.AstMethodBodyBuilder.createMethodBody(AstMethodBodyBuilder.java:99)
        //     at com.strobel.decompiler.languages.java.ast.AstBuilder.createMethodBody(AstBuilder.java:782)
        //     at com.strobel.decompiler.languages.java.ast.AstBuilder.createMethod(AstBuilder.java:675)
        //     at com.strobel.decompiler.languages.java.ast.AstBuilder.addTypeMembers(AstBuilder.java:552)
        //     at com.strobel.decompiler.languages.java.ast.AstBuilder.createTypeCore(AstBuilder.java:519)
        //     at com.strobel.decompiler.languages.java.ast.AstBuilder.createTypeNoCache(AstBuilder.java:161)
        //     at com.strobel.decompiler.languages.java.ast.AstBuilder.createType(AstBuilder.java:150)
        //     at com.strobel.decompiler.languages.java.ast.AstBuilder.addType(AstBuilder.java:125)
        //     at com.strobel.decompiler.languages.java.JavaLanguage.buildAst(JavaLanguage.java:71)
        //     at com.strobel.decompiler.languages.java.JavaLanguage.decompileType(JavaLanguage.java:59)
        //     at com.strobel.decompiler.DecompilerDriver.decompileType(DecompilerDriver.java:330)
        //     at com.strobel.decompiler.DecompilerDriver.decompileJar(DecompilerDriver.java:251)
        //     at com.strobel.decompiler.DecompilerDriver.main(DecompilerDriver.java:126)
        // 
        throw new IllegalStateException("An error occurred while decompiling this method.");
    }
    
    public synchronized boolean getBExplDatAnniv() {
        return this.bExplDatAnniv;
    }
    
    public synchronized boolean getbExplDatAnniv() {
        return this.bExplDatAnniv;
    }
    
    public void setBExplDatAnniv(final boolean p0) {
        // 
        // This method could not be decompiled.
        // 
        // Original Bytecode:
        // 
        //     3: aload_3        
        //     4: monitorexit    
        //     5: athrow         
        //     6: aload_0        
        //     7: dup            
        //     8: astore_3       
        //     9: monitorenter   
        //    10: aload_0        
        //    11: getfield        facade/characters/wmedef/PostBeatMixinInfoWME.bExplDatAnniv:Z
        //    14: istore_2       
        //    15: aload_0        
        //    16: iload_1        
        //    17: putfield        facade/characters/wmedef/PostBeatMixinInfoWME.bExplDatAnniv:Z
        //    20: aload_3        
        //    21: monitorexit    
        //    22: aload_0        
        //    23: getfield        facade/characters/wmedef/PostBeatMixinInfoWME.__support:Ljava/beans/PropertyChangeSupport;
        //    26: ldc             "bExplDatAnniv"
        //    28: iload_2        
        //    29: iload_1        
        //    30: invokevirtual   java/beans/PropertyChangeSupport.firePropertyChange:(Ljava/lang/String;ZZ)V
        //    33: return         
        //    Exceptions:
        //  Try           Handler
        //  Start  End    Start  End    Type
        //  -----  -----  -----  -----  ----
        //  3      5      3      6      Any
        //  10     22     3      6      Any
        // 
        // The error that occurred was:
        // 
        // java.util.ConcurrentModificationException
        //     at java.util.ArrayList$Itr.checkForComodification(Unknown Source)
        //     at java.util.ArrayList$Itr.next(Unknown Source)
        //     at com.strobel.decompiler.ast.AstBuilder.convertLocalVariables(AstBuilder.java:2863)
        //     at com.strobel.decompiler.ast.AstBuilder.performStackAnalysis(AstBuilder.java:2445)
        //     at com.strobel.decompiler.ast.AstBuilder.build(AstBuilder.java:108)
        //     at com.strobel.decompiler.languages.java.ast.AstMethodBodyBuilder.createMethodBody(AstMethodBodyBuilder.java:211)
        //     at com.strobel.decompiler.languages.java.ast.AstMethodBodyBuilder.createMethodBody(AstMethodBodyBuilder.java:99)
        //     at com.strobel.decompiler.languages.java.ast.AstBuilder.createMethodBody(AstBuilder.java:782)
        //     at com.strobel.decompiler.languages.java.ast.AstBuilder.createMethod(AstBuilder.java:675)
        //     at com.strobel.decompiler.languages.java.ast.AstBuilder.addTypeMembers(AstBuilder.java:552)
        //     at com.strobel.decompiler.languages.java.ast.AstBuilder.createTypeCore(AstBuilder.java:519)
        //     at com.strobel.decompiler.languages.java.ast.AstBuilder.createTypeNoCache(AstBuilder.java:161)
        //     at com.strobel.decompiler.languages.java.ast.AstBuilder.createType(AstBuilder.java:150)
        //     at com.strobel.decompiler.languages.java.ast.AstBuilder.addType(AstBuilder.java:125)
        //     at com.strobel.decompiler.languages.java.JavaLanguage.buildAst(JavaLanguage.java:71)
        //     at com.strobel.decompiler.languages.java.JavaLanguage.decompileType(JavaLanguage.java:59)
        //     at com.strobel.decompiler.DecompilerDriver.decompileType(DecompilerDriver.java:330)
        //     at com.strobel.decompiler.DecompilerDriver.decompileJar(DecompilerDriver.java:251)
        //     at com.strobel.decompiler.DecompilerDriver.main(DecompilerDriver.java:126)
        // 
        throw new IllegalStateException("An error occurred while decompiling this method.");
    }
    
    public synchronized boolean getBRM_Italy() {
        return this.bRM_Italy;
    }
    
    public synchronized boolean getbRM_Italy() {
        return this.bRM_Italy;
    }
    
    public void setBRM_Italy(final boolean p0) {
        // 
        // This method could not be decompiled.
        // 
        // Original Bytecode:
        // 
        //     3: aload_3        
        //     4: monitorexit    
        //     5: athrow         
        //     6: aload_0        
        //     7: dup            
        //     8: astore_3       
        //     9: monitorenter   
        //    10: aload_0        
        //    11: getfield        facade/characters/wmedef/PostBeatMixinInfoWME.bRM_Italy:Z
        //    14: istore_2       
        //    15: aload_0        
        //    16: iload_1        
        //    17: putfield        facade/characters/wmedef/PostBeatMixinInfoWME.bRM_Italy:Z
        //    20: aload_3        
        //    21: monitorexit    
        //    22: aload_0        
        //    23: getfield        facade/characters/wmedef/PostBeatMixinInfoWME.__support:Ljava/beans/PropertyChangeSupport;
        //    26: ldc             "bRM_Italy"
        //    28: iload_2        
        //    29: iload_1        
        //    30: invokevirtual   java/beans/PropertyChangeSupport.firePropertyChange:(Ljava/lang/String;ZZ)V
        //    33: return         
        //    Exceptions:
        //  Try           Handler
        //  Start  End    Start  End    Type
        //  -----  -----  -----  -----  ----
        //  3      5      3      6      Any
        //  10     22     3      6      Any
        // 
        // The error that occurred was:
        // 
        // java.util.ConcurrentModificationException
        //     at java.util.ArrayList$Itr.checkForComodification(Unknown Source)
        //     at java.util.ArrayList$Itr.next(Unknown Source)
        //     at com.strobel.decompiler.ast.AstBuilder.convertLocalVariables(AstBuilder.java:2863)
        //     at com.strobel.decompiler.ast.AstBuilder.performStackAnalysis(AstBuilder.java:2445)
        //     at com.strobel.decompiler.ast.AstBuilder.build(AstBuilder.java:108)
        //     at com.strobel.decompiler.languages.java.ast.AstMethodBodyBuilder.createMethodBody(AstMethodBodyBuilder.java:211)
        //     at com.strobel.decompiler.languages.java.ast.AstMethodBodyBuilder.createMethodBody(AstMethodBodyBuilder.java:99)
        //     at com.strobel.decompiler.languages.java.ast.AstBuilder.createMethodBody(AstBuilder.java:782)
        //     at com.strobel.decompiler.languages.java.ast.AstBuilder.createMethod(AstBuilder.java:675)
        //     at com.strobel.decompiler.languages.java.ast.AstBuilder.addTypeMembers(AstBuilder.java:552)
        //     at com.strobel.decompiler.languages.java.ast.AstBuilder.createTypeCore(AstBuilder.java:519)
        //     at com.strobel.decompiler.languages.java.ast.AstBuilder.createTypeNoCache(AstBuilder.java:161)
        //     at com.strobel.decompiler.languages.java.ast.AstBuilder.createType(AstBuilder.java:150)
        //     at com.strobel.decompiler.languages.java.ast.AstBuilder.addType(AstBuilder.java:125)
        //     at com.strobel.decompiler.languages.java.JavaLanguage.buildAst(JavaLanguage.java:71)
        //     at com.strobel.decompiler.languages.java.JavaLanguage.decompileType(JavaLanguage.java:59)
        //     at com.strobel.decompiler.DecompilerDriver.decompileType(DecompilerDriver.java:330)
        //     at com.strobel.decompiler.DecompilerDriver.decompileJar(DecompilerDriver.java:251)
        //     at com.strobel.decompiler.DecompilerDriver.main(DecompilerDriver.java:126)
        // 
        throw new IllegalStateException("An error occurred while decompiling this method.");
    }
    
    public synchronized boolean getBFAskDrinks() {
        return this.bFAskDrinks;
    }
    
    public synchronized boolean getbFAskDrinks() {
        return this.bFAskDrinks;
    }
    
    public void setBFAskDrinks(final boolean p0) {
        // 
        // This method could not be decompiled.
        // 
        // Original Bytecode:
        // 
        //     3: aload_3        
        //     4: monitorexit    
        //     5: athrow         
        //     6: aload_0        
        //     7: dup            
        //     8: astore_3       
        //     9: monitorenter   
        //    10: aload_0        
        //    11: getfield        facade/characters/wmedef/PostBeatMixinInfoWME.bFAskDrinks:Z
        //    14: istore_2       
        //    15: aload_0        
        //    16: iload_1        
        //    17: putfield        facade/characters/wmedef/PostBeatMixinInfoWME.bFAskDrinks:Z
        //    20: aload_3        
        //    21: monitorexit    
        //    22: aload_0        
        //    23: getfield        facade/characters/wmedef/PostBeatMixinInfoWME.__support:Ljava/beans/PropertyChangeSupport;
        //    26: ldc             "bFAskDrinks"
        //    28: iload_2        
        //    29: iload_1        
        //    30: invokevirtual   java/beans/PropertyChangeSupport.firePropertyChange:(Ljava/lang/String;ZZ)V
        //    33: return         
        //    Exceptions:
        //  Try           Handler
        //  Start  End    Start  End    Type
        //  -----  -----  -----  -----  ----
        //  3      5      3      6      Any
        //  10     22     3      6      Any
        // 
        // The error that occurred was:
        // 
        // java.util.ConcurrentModificationException
        //     at java.util.ArrayList$Itr.checkForComodification(Unknown Source)
        //     at java.util.ArrayList$Itr.next(Unknown Source)
        //     at com.strobel.decompiler.ast.AstBuilder.convertLocalVariables(AstBuilder.java:2863)
        //     at com.strobel.decompiler.ast.AstBuilder.performStackAnalysis(AstBuilder.java:2445)
        //     at com.strobel.decompiler.ast.AstBuilder.build(AstBuilder.java:108)
        //     at com.strobel.decompiler.languages.java.ast.AstMethodBodyBuilder.createMethodBody(AstMethodBodyBuilder.java:211)
        //     at com.strobel.decompiler.languages.java.ast.AstMethodBodyBuilder.createMethodBody(AstMethodBodyBuilder.java:99)
        //     at com.strobel.decompiler.languages.java.ast.AstBuilder.createMethodBody(AstBuilder.java:782)
        //     at com.strobel.decompiler.languages.java.ast.AstBuilder.createMethod(AstBuilder.java:675)
        //     at com.strobel.decompiler.languages.java.ast.AstBuilder.addTypeMembers(AstBuilder.java:552)
        //     at com.strobel.decompiler.languages.java.ast.AstBuilder.createTypeCore(AstBuilder.java:519)
        //     at com.strobel.decompiler.languages.java.ast.AstBuilder.createTypeNoCache(AstBuilder.java:161)
        //     at com.strobel.decompiler.languages.java.ast.AstBuilder.createType(AstBuilder.java:150)
        //     at com.strobel.decompiler.languages.java.ast.AstBuilder.addType(AstBuilder.java:125)
        //     at com.strobel.decompiler.languages.java.JavaLanguage.buildAst(JavaLanguage.java:71)
        //     at com.strobel.decompiler.languages.java.JavaLanguage.decompileType(JavaLanguage.java:59)
        //     at com.strobel.decompiler.DecompilerDriver.decompileType(DecompilerDriver.java:330)
        //     at com.strobel.decompiler.DecompilerDriver.decompileJar(DecompilerDriver.java:251)
        //     at com.strobel.decompiler.DecompilerDriver.main(DecompilerDriver.java:126)
        // 
        throw new IllegalStateException("An error occurred while decompiling this method.");
    }
    
    public synchronized boolean getBPhoneCall() {
        return this.bPhoneCall;
    }
    
    public synchronized boolean getbPhoneCall() {
        return this.bPhoneCall;
    }
    
    public void setBPhoneCall(final boolean p0) {
        // 
        // This method could not be decompiled.
        // 
        // Original Bytecode:
        // 
        //     3: aload_3        
        //     4: monitorexit    
        //     5: athrow         
        //     6: aload_0        
        //     7: dup            
        //     8: astore_3       
        //     9: monitorenter   
        //    10: aload_0        
        //    11: getfield        facade/characters/wmedef/PostBeatMixinInfoWME.bPhoneCall:Z
        //    14: istore_2       
        //    15: aload_0        
        //    16: iload_1        
        //    17: putfield        facade/characters/wmedef/PostBeatMixinInfoWME.bPhoneCall:Z
        //    20: aload_3        
        //    21: monitorexit    
        //    22: aload_0        
        //    23: getfield        facade/characters/wmedef/PostBeatMixinInfoWME.__support:Ljava/beans/PropertyChangeSupport;
        //    26: ldc             "bPhoneCall"
        //    28: iload_2        
        //    29: iload_1        
        //    30: invokevirtual   java/beans/PropertyChangeSupport.firePropertyChange:(Ljava/lang/String;ZZ)V
        //    33: return         
        //    Exceptions:
        //  Try           Handler
        //  Start  End    Start  End    Type
        //  -----  -----  -----  -----  ----
        //  3      5      3      6      Any
        //  10     22     3      6      Any
        // 
        // The error that occurred was:
        // 
        // java.util.ConcurrentModificationException
        //     at java.util.ArrayList$Itr.checkForComodification(Unknown Source)
        //     at java.util.ArrayList$Itr.next(Unknown Source)
        //     at com.strobel.decompiler.ast.AstBuilder.convertLocalVariables(AstBuilder.java:2863)
        //     at com.strobel.decompiler.ast.AstBuilder.performStackAnalysis(AstBuilder.java:2445)
        //     at com.strobel.decompiler.ast.AstBuilder.build(AstBuilder.java:108)
        //     at com.strobel.decompiler.languages.java.ast.AstMethodBodyBuilder.createMethodBody(AstMethodBodyBuilder.java:211)
        //     at com.strobel.decompiler.languages.java.ast.AstMethodBodyBuilder.createMethodBody(AstMethodBodyBuilder.java:99)
        //     at com.strobel.decompiler.languages.java.ast.AstBuilder.createMethodBody(AstBuilder.java:782)
        //     at com.strobel.decompiler.languages.java.ast.AstBuilder.createMethod(AstBuilder.java:675)
        //     at com.strobel.decompiler.languages.java.ast.AstBuilder.addTypeMembers(AstBuilder.java:552)
        //     at com.strobel.decompiler.languages.java.ast.AstBuilder.createTypeCore(AstBuilder.java:519)
        //     at com.strobel.decompiler.languages.java.ast.AstBuilder.createTypeNoCache(AstBuilder.java:161)
        //     at com.strobel.decompiler.languages.java.ast.AstBuilder.createType(AstBuilder.java:150)
        //     at com.strobel.decompiler.languages.java.ast.AstBuilder.addType(AstBuilder.java:125)
        //     at com.strobel.decompiler.languages.java.JavaLanguage.buildAst(JavaLanguage.java:71)
        //     at com.strobel.decompiler.languages.java.JavaLanguage.decompileType(JavaLanguage.java:59)
        //     at com.strobel.decompiler.DecompilerDriver.decompileType(DecompilerDriver.java:330)
        //     at com.strobel.decompiler.DecompilerDriver.decompileJar(DecompilerDriver.java:251)
        //     at com.strobel.decompiler.DecompilerDriver.main(DecompilerDriver.java:126)
        // 
        throw new IllegalStateException("An error occurred while decompiling this method.");
    }
    
    public PostBeatMixinInfoWME() {
        this.beatGGreetsP = -1;
        this.beatArtistAdv = -1;
        this.beatExplDatAnniv = -1;
        this.beatFAskDrink = -1;
        this.beatRockyMarriage = -1;
        this.beatRockyMarriage_WorkTable = -1;
        this.beatPhoneCall = -1;
        this.bGGreetsP = false;
        this.bAA_decorating_txnIn = false;
        this.bAA_decorating_txnOut = false;
        this.bAA_decorating_styleApt = false;
        this.bAA_decorating_couch = false;
        this.bAA_decorating_armoire = false;
        this.bAA_decorating_trinkets = false;
        this.bAA_decorating_paintings = false;
        this.bAA_decorating_weddingPicture = false;
        this.bAA_decorating_view = false;
        this.bAA_decorating_sideTable = false;
        this.bAA_decorating_rug = false;
        this.bExplDatAnniv = false;
        this.bRM_Italy = false;
        this.bFAskDrinks = false;
        this.bPhoneCall = false;
    }
}
