package dramaman.runtime;

import javax.swing.JComboBox;
import wm.WMEFieldEditor;
import facade.util.PrintUtilities;
import facade.util.BeatID;
import wm.WME;

public class StoryStatusWME extends WME implements BeatID, DramaManagerConstants
{
    private int beatCount;
    private int previousBeat;
    private int currentBeat;
    private int affinity;
    private int storySegment;
    private boolean dramaManagerEnabled;
    private int beatCountOfLastGreetingBeat;
    private int storyTopicBeatCount;
    private long NLPProcessingStarted;
    private static final /* synthetic */ boolean $noassert;
    
    public String formatAffinity() {
        return PrintUtilities.affinity_EnumToString(this.getAffinity());
    }
    
    public String formatPreviousBeat() {
        return PrintUtilities.beatID_EnumToString(this.getPreviousBeat());
    }
    
    public String formatCurrentBeat() {
        return PrintUtilities.beatID_EnumToString(this.getCurrentBeat());
    }
    
    public String formatStorySegment() {
        return PrintUtilities.storySegment_EnumToString(this.getStorySegment());
    }
    
    public synchronized int getBeatCount() {
        return this.beatCount;
    }
    
    public void setBeatCount(final int p0) {
        // 
        // This method could not be decompiled.
        // 
        // Original Bytecode:
        // 
        //     3: aload_3        
        //     4: monitorexit    
        //     5: athrow         
        //     6: aload_0        
        //     7: dup            
        //     8: astore_3       
        //     9: monitorenter   
        //    10: aload_0        
        //    11: getfield        dramaman/runtime/StoryStatusWME.beatCount:I
        //    14: istore_2       
        //    15: aload_0        
        //    16: iload_1        
        //    17: putfield        dramaman/runtime/StoryStatusWME.beatCount:I
        //    20: aload_3        
        //    21: monitorexit    
        //    22: aload_0        
        //    23: getfield        dramaman/runtime/StoryStatusWME.__support:Ljava/beans/PropertyChangeSupport;
        //    26: ldc             "beatCount"
        //    28: iload_2        
        //    29: iload_1        
        //    30: invokevirtual   java/beans/PropertyChangeSupport.firePropertyChange:(Ljava/lang/String;II)V
        //    33: return         
        //    Exceptions:
        //  Try           Handler
        //  Start  End    Start  End    Type
        //  -----  -----  -----  -----  ----
        //  3      5      3      6      Any
        //  10     22     3      6      Any
        // 
        // The error that occurred was:
        // 
        // java.util.ConcurrentModificationException
        //     at java.util.ArrayList$Itr.checkForComodification(Unknown Source)
        //     at java.util.ArrayList$Itr.next(Unknown Source)
        //     at com.strobel.decompiler.ast.AstBuilder.convertLocalVariables(AstBuilder.java:2863)
        //     at com.strobel.decompiler.ast.AstBuilder.performStackAnalysis(AstBuilder.java:2445)
        //     at com.strobel.decompiler.ast.AstBuilder.build(AstBuilder.java:108)
        //     at com.strobel.decompiler.languages.java.ast.AstMethodBodyBuilder.createMethodBody(AstMethodBodyBuilder.java:211)
        //     at com.strobel.decompiler.languages.java.ast.AstMethodBodyBuilder.createMethodBody(AstMethodBodyBuilder.java:99)
        //     at com.strobel.decompiler.languages.java.ast.AstBuilder.createMethodBody(AstBuilder.java:782)
        //     at com.strobel.decompiler.languages.java.ast.AstBuilder.createMethod(AstBuilder.java:675)
        //     at com.strobel.decompiler.languages.java.ast.AstBuilder.addTypeMembers(AstBuilder.java:552)
        //     at com.strobel.decompiler.languages.java.ast.AstBuilder.createTypeCore(AstBuilder.java:519)
        //     at com.strobel.decompiler.languages.java.ast.AstBuilder.createTypeNoCache(AstBuilder.java:161)
        //     at com.strobel.decompiler.languages.java.ast.AstBuilder.createType(AstBuilder.java:150)
        //     at com.strobel.decompiler.languages.java.ast.AstBuilder.addType(AstBuilder.java:125)
        //     at com.strobel.decompiler.languages.java.JavaLanguage.buildAst(JavaLanguage.java:71)
        //     at com.strobel.decompiler.languages.java.JavaLanguage.decompileType(JavaLanguage.java:59)
        //     at com.strobel.decompiler.DecompilerDriver.decompileType(DecompilerDriver.java:330)
        //     at com.strobel.decompiler.DecompilerDriver.decompileJar(DecompilerDriver.java:251)
        //     at com.strobel.decompiler.DecompilerDriver.main(DecompilerDriver.java:126)
        // 
        throw new IllegalStateException("An error occurred while decompiling this method.");
    }
    
    public synchronized int getPreviousBeat() {
        return this.previousBeat;
    }
    
    public void setPreviousBeat(final int p0) {
        // 
        // This method could not be decompiled.
        // 
        // Original Bytecode:
        // 
        //     3: aload_3        
        //     4: monitorexit    
        //     5: athrow         
        //     6: aload_0        
        //     7: dup            
        //     8: astore_3       
        //     9: monitorenter   
        //    10: aload_0        
        //    11: getfield        dramaman/runtime/StoryStatusWME.previousBeat:I
        //    14: istore_2       
        //    15: aload_0        
        //    16: iload_1        
        //    17: putfield        dramaman/runtime/StoryStatusWME.previousBeat:I
        //    20: aload_3        
        //    21: monitorexit    
        //    22: aload_0        
        //    23: getfield        dramaman/runtime/StoryStatusWME.__support:Ljava/beans/PropertyChangeSupport;
        //    26: ldc             "previousBeat"
        //    28: iload_2        
        //    29: iload_1        
        //    30: invokevirtual   java/beans/PropertyChangeSupport.firePropertyChange:(Ljava/lang/String;II)V
        //    33: return         
        //    Exceptions:
        //  Try           Handler
        //  Start  End    Start  End    Type
        //  -----  -----  -----  -----  ----
        //  3      5      3      6      Any
        //  10     22     3      6      Any
        // 
        // The error that occurred was:
        // 
        // java.util.ConcurrentModificationException
        //     at java.util.ArrayList$Itr.checkForComodification(Unknown Source)
        //     at java.util.ArrayList$Itr.next(Unknown Source)
        //     at com.strobel.decompiler.ast.AstBuilder.convertLocalVariables(AstBuilder.java:2863)
        //     at com.strobel.decompiler.ast.AstBuilder.performStackAnalysis(AstBuilder.java:2445)
        //     at com.strobel.decompiler.ast.AstBuilder.build(AstBuilder.java:108)
        //     at com.strobel.decompiler.languages.java.ast.AstMethodBodyBuilder.createMethodBody(AstMethodBodyBuilder.java:211)
        //     at com.strobel.decompiler.languages.java.ast.AstMethodBodyBuilder.createMethodBody(AstMethodBodyBuilder.java:99)
        //     at com.strobel.decompiler.languages.java.ast.AstBuilder.createMethodBody(AstBuilder.java:782)
        //     at com.strobel.decompiler.languages.java.ast.AstBuilder.createMethod(AstBuilder.java:675)
        //     at com.strobel.decompiler.languages.java.ast.AstBuilder.addTypeMembers(AstBuilder.java:552)
        //     at com.strobel.decompiler.languages.java.ast.AstBuilder.createTypeCore(AstBuilder.java:519)
        //     at com.strobel.decompiler.languages.java.ast.AstBuilder.createTypeNoCache(AstBuilder.java:161)
        //     at com.strobel.decompiler.languages.java.ast.AstBuilder.createType(AstBuilder.java:150)
        //     at com.strobel.decompiler.languages.java.ast.AstBuilder.addType(AstBuilder.java:125)
        //     at com.strobel.decompiler.languages.java.JavaLanguage.buildAst(JavaLanguage.java:71)
        //     at com.strobel.decompiler.languages.java.JavaLanguage.decompileType(JavaLanguage.java:59)
        //     at com.strobel.decompiler.DecompilerDriver.decompileType(DecompilerDriver.java:330)
        //     at com.strobel.decompiler.DecompilerDriver.decompileJar(DecompilerDriver.java:251)
        //     at com.strobel.decompiler.DecompilerDriver.main(DecompilerDriver.java:126)
        // 
        throw new IllegalStateException("An error occurred while decompiling this method.");
    }
    
    public synchronized int getCurrentBeat() {
        return this.currentBeat;
    }
    
    public void setCurrentBeat(final int p0) {
        // 
        // This method could not be decompiled.
        // 
        // Original Bytecode:
        // 
        //     3: aload_3        
        //     4: monitorexit    
        //     5: athrow         
        //     6: aload_0        
        //     7: dup            
        //     8: astore_3       
        //     9: monitorenter   
        //    10: aload_0        
        //    11: getfield        dramaman/runtime/StoryStatusWME.currentBeat:I
        //    14: istore_2       
        //    15: aload_0        
        //    16: iload_1        
        //    17: putfield        dramaman/runtime/StoryStatusWME.currentBeat:I
        //    20: aload_3        
        //    21: monitorexit    
        //    22: aload_0        
        //    23: getfield        dramaman/runtime/StoryStatusWME.__support:Ljava/beans/PropertyChangeSupport;
        //    26: ldc             "currentBeat"
        //    28: iload_2        
        //    29: iload_1        
        //    30: invokevirtual   java/beans/PropertyChangeSupport.firePropertyChange:(Ljava/lang/String;II)V
        //    33: return         
        //    Exceptions:
        //  Try           Handler
        //  Start  End    Start  End    Type
        //  -----  -----  -----  -----  ----
        //  3      5      3      6      Any
        //  10     22     3      6      Any
        // 
        // The error that occurred was:
        // 
        // java.util.ConcurrentModificationException
        //     at java.util.ArrayList$Itr.checkForComodification(Unknown Source)
        //     at java.util.ArrayList$Itr.next(Unknown Source)
        //     at com.strobel.decompiler.ast.AstBuilder.convertLocalVariables(AstBuilder.java:2863)
        //     at com.strobel.decompiler.ast.AstBuilder.performStackAnalysis(AstBuilder.java:2445)
        //     at com.strobel.decompiler.ast.AstBuilder.build(AstBuilder.java:108)
        //     at com.strobel.decompiler.languages.java.ast.AstMethodBodyBuilder.createMethodBody(AstMethodBodyBuilder.java:211)
        //     at com.strobel.decompiler.languages.java.ast.AstMethodBodyBuilder.createMethodBody(AstMethodBodyBuilder.java:99)
        //     at com.strobel.decompiler.languages.java.ast.AstBuilder.createMethodBody(AstBuilder.java:782)
        //     at com.strobel.decompiler.languages.java.ast.AstBuilder.createMethod(AstBuilder.java:675)
        //     at com.strobel.decompiler.languages.java.ast.AstBuilder.addTypeMembers(AstBuilder.java:552)
        //     at com.strobel.decompiler.languages.java.ast.AstBuilder.createTypeCore(AstBuilder.java:519)
        //     at com.strobel.decompiler.languages.java.ast.AstBuilder.createTypeNoCache(AstBuilder.java:161)
        //     at com.strobel.decompiler.languages.java.ast.AstBuilder.createType(AstBuilder.java:150)
        //     at com.strobel.decompiler.languages.java.ast.AstBuilder.addType(AstBuilder.java:125)
        //     at com.strobel.decompiler.languages.java.JavaLanguage.buildAst(JavaLanguage.java:71)
        //     at com.strobel.decompiler.languages.java.JavaLanguage.decompileType(JavaLanguage.java:59)
        //     at com.strobel.decompiler.DecompilerDriver.decompileType(DecompilerDriver.java:330)
        //     at com.strobel.decompiler.DecompilerDriver.decompileJar(DecompilerDriver.java:251)
        //     at com.strobel.decompiler.DecompilerDriver.main(DecompilerDriver.java:126)
        // 
        throw new IllegalStateException("An error occurred while decompiling this method.");
    }
    
    public synchronized int getAffinity() {
        return this.affinity;
    }
    
    public void setAffinity(final int p0) {
        // 
        // This method could not be decompiled.
        // 
        // Original Bytecode:
        // 
        //     3: aload_3        
        //     4: monitorexit    
        //     5: athrow         
        //     6: aload_0        
        //     7: dup            
        //     8: astore_3       
        //     9: monitorenter   
        //    10: aload_0        
        //    11: getfield        dramaman/runtime/StoryStatusWME.affinity:I
        //    14: istore_2       
        //    15: aload_0        
        //    16: iload_1        
        //    17: putfield        dramaman/runtime/StoryStatusWME.affinity:I
        //    20: aload_3        
        //    21: monitorexit    
        //    22: aload_0        
        //    23: getfield        dramaman/runtime/StoryStatusWME.__support:Ljava/beans/PropertyChangeSupport;
        //    26: ldc             "affinity"
        //    28: iload_2        
        //    29: iload_1        
        //    30: invokevirtual   java/beans/PropertyChangeSupport.firePropertyChange:(Ljava/lang/String;II)V
        //    33: return         
        //    Exceptions:
        //  Try           Handler
        //  Start  End    Start  End    Type
        //  -----  -----  -----  -----  ----
        //  3      5      3      6      Any
        //  10     22     3      6      Any
        // 
        // The error that occurred was:
        // 
        // java.util.ConcurrentModificationException
        //     at java.util.ArrayList$Itr.checkForComodification(Unknown Source)
        //     at java.util.ArrayList$Itr.next(Unknown Source)
        //     at com.strobel.decompiler.ast.AstBuilder.convertLocalVariables(AstBuilder.java:2863)
        //     at com.strobel.decompiler.ast.AstBuilder.performStackAnalysis(AstBuilder.java:2445)
        //     at com.strobel.decompiler.ast.AstBuilder.build(AstBuilder.java:108)
        //     at com.strobel.decompiler.languages.java.ast.AstMethodBodyBuilder.createMethodBody(AstMethodBodyBuilder.java:211)
        //     at com.strobel.decompiler.languages.java.ast.AstMethodBodyBuilder.createMethodBody(AstMethodBodyBuilder.java:99)
        //     at com.strobel.decompiler.languages.java.ast.AstBuilder.createMethodBody(AstBuilder.java:782)
        //     at com.strobel.decompiler.languages.java.ast.AstBuilder.createMethod(AstBuilder.java:675)
        //     at com.strobel.decompiler.languages.java.ast.AstBuilder.addTypeMembers(AstBuilder.java:552)
        //     at com.strobel.decompiler.languages.java.ast.AstBuilder.createTypeCore(AstBuilder.java:519)
        //     at com.strobel.decompiler.languages.java.ast.AstBuilder.createTypeNoCache(AstBuilder.java:161)
        //     at com.strobel.decompiler.languages.java.ast.AstBuilder.createType(AstBuilder.java:150)
        //     at com.strobel.decompiler.languages.java.ast.AstBuilder.addType(AstBuilder.java:125)
        //     at com.strobel.decompiler.languages.java.JavaLanguage.buildAst(JavaLanguage.java:71)
        //     at com.strobel.decompiler.languages.java.JavaLanguage.decompileType(JavaLanguage.java:59)
        //     at com.strobel.decompiler.DecompilerDriver.decompileType(DecompilerDriver.java:330)
        //     at com.strobel.decompiler.DecompilerDriver.decompileJar(DecompilerDriver.java:251)
        //     at com.strobel.decompiler.DecompilerDriver.main(DecompilerDriver.java:126)
        // 
        throw new IllegalStateException("An error occurred while decompiling this method.");
    }
    
    public synchronized int getStorySegment() {
        return this.storySegment;
    }
    
    public void setStorySegment(final int p0) {
        // 
        // This method could not be decompiled.
        // 
        // Original Bytecode:
        // 
        //     3: aload_3        
        //     4: monitorexit    
        //     5: athrow         
        //     6: aload_0        
        //     7: dup            
        //     8: astore_3       
        //     9: monitorenter   
        //    10: aload_0        
        //    11: getfield        dramaman/runtime/StoryStatusWME.storySegment:I
        //    14: istore_2       
        //    15: aload_0        
        //    16: iload_1        
        //    17: putfield        dramaman/runtime/StoryStatusWME.storySegment:I
        //    20: aload_3        
        //    21: monitorexit    
        //    22: aload_0        
        //    23: getfield        dramaman/runtime/StoryStatusWME.__support:Ljava/beans/PropertyChangeSupport;
        //    26: ldc             "storySegment"
        //    28: iload_2        
        //    29: iload_1        
        //    30: invokevirtual   java/beans/PropertyChangeSupport.firePropertyChange:(Ljava/lang/String;II)V
        //    33: return         
        //    Exceptions:
        //  Try           Handler
        //  Start  End    Start  End    Type
        //  -----  -----  -----  -----  ----
        //  3      5      3      6      Any
        //  10     22     3      6      Any
        // 
        // The error that occurred was:
        // 
        // java.util.ConcurrentModificationException
        //     at java.util.ArrayList$Itr.checkForComodification(Unknown Source)
        //     at java.util.ArrayList$Itr.next(Unknown Source)
        //     at com.strobel.decompiler.ast.AstBuilder.convertLocalVariables(AstBuilder.java:2863)
        //     at com.strobel.decompiler.ast.AstBuilder.performStackAnalysis(AstBuilder.java:2445)
        //     at com.strobel.decompiler.ast.AstBuilder.build(AstBuilder.java:108)
        //     at com.strobel.decompiler.languages.java.ast.AstMethodBodyBuilder.createMethodBody(AstMethodBodyBuilder.java:211)
        //     at com.strobel.decompiler.languages.java.ast.AstMethodBodyBuilder.createMethodBody(AstMethodBodyBuilder.java:99)
        //     at com.strobel.decompiler.languages.java.ast.AstBuilder.createMethodBody(AstBuilder.java:782)
        //     at com.strobel.decompiler.languages.java.ast.AstBuilder.createMethod(AstBuilder.java:675)
        //     at com.strobel.decompiler.languages.java.ast.AstBuilder.addTypeMembers(AstBuilder.java:552)
        //     at com.strobel.decompiler.languages.java.ast.AstBuilder.createTypeCore(AstBuilder.java:519)
        //     at com.strobel.decompiler.languages.java.ast.AstBuilder.createTypeNoCache(AstBuilder.java:161)
        //     at com.strobel.decompiler.languages.java.ast.AstBuilder.createType(AstBuilder.java:150)
        //     at com.strobel.decompiler.languages.java.ast.AstBuilder.addType(AstBuilder.java:125)
        //     at com.strobel.decompiler.languages.java.JavaLanguage.buildAst(JavaLanguage.java:71)
        //     at com.strobel.decompiler.languages.java.JavaLanguage.decompileType(JavaLanguage.java:59)
        //     at com.strobel.decompiler.DecompilerDriver.decompileType(DecompilerDriver.java:330)
        //     at com.strobel.decompiler.DecompilerDriver.decompileJar(DecompilerDriver.java:251)
        //     at com.strobel.decompiler.DecompilerDriver.main(DecompilerDriver.java:126)
        // 
        throw new IllegalStateException("An error occurred while decompiling this method.");
    }
    
    public synchronized boolean getDramaManagerEnabled() {
        return this.dramaManagerEnabled;
    }
    
    public void setDramaManagerEnabled(final boolean p0) {
        // 
        // This method could not be decompiled.
        // 
        // Original Bytecode:
        // 
        //     3: aload_3        
        //     4: monitorexit    
        //     5: athrow         
        //     6: aload_0        
        //     7: dup            
        //     8: astore_3       
        //     9: monitorenter   
        //    10: aload_0        
        //    11: getfield        dramaman/runtime/StoryStatusWME.dramaManagerEnabled:Z
        //    14: istore_2       
        //    15: aload_0        
        //    16: iload_1        
        //    17: putfield        dramaman/runtime/StoryStatusWME.dramaManagerEnabled:Z
        //    20: aload_3        
        //    21: monitorexit    
        //    22: aload_0        
        //    23: getfield        dramaman/runtime/StoryStatusWME.__support:Ljava/beans/PropertyChangeSupport;
        //    26: ldc             "dramaManagerEnabled"
        //    28: iload_2        
        //    29: iload_1        
        //    30: invokevirtual   java/beans/PropertyChangeSupport.firePropertyChange:(Ljava/lang/String;ZZ)V
        //    33: return         
        //    Exceptions:
        //  Try           Handler
        //  Start  End    Start  End    Type
        //  -----  -----  -----  -----  ----
        //  3      5      3      6      Any
        //  10     22     3      6      Any
        // 
        // The error that occurred was:
        // 
        // java.util.ConcurrentModificationException
        //     at java.util.ArrayList$Itr.checkForComodification(Unknown Source)
        //     at java.util.ArrayList$Itr.next(Unknown Source)
        //     at com.strobel.decompiler.ast.AstBuilder.convertLocalVariables(AstBuilder.java:2863)
        //     at com.strobel.decompiler.ast.AstBuilder.performStackAnalysis(AstBuilder.java:2445)
        //     at com.strobel.decompiler.ast.AstBuilder.build(AstBuilder.java:108)
        //     at com.strobel.decompiler.languages.java.ast.AstMethodBodyBuilder.createMethodBody(AstMethodBodyBuilder.java:211)
        //     at com.strobel.decompiler.languages.java.ast.AstMethodBodyBuilder.createMethodBody(AstMethodBodyBuilder.java:99)
        //     at com.strobel.decompiler.languages.java.ast.AstBuilder.createMethodBody(AstBuilder.java:782)
        //     at com.strobel.decompiler.languages.java.ast.AstBuilder.createMethod(AstBuilder.java:675)
        //     at com.strobel.decompiler.languages.java.ast.AstBuilder.addTypeMembers(AstBuilder.java:552)
        //     at com.strobel.decompiler.languages.java.ast.AstBuilder.createTypeCore(AstBuilder.java:519)
        //     at com.strobel.decompiler.languages.java.ast.AstBuilder.createTypeNoCache(AstBuilder.java:161)
        //     at com.strobel.decompiler.languages.java.ast.AstBuilder.createType(AstBuilder.java:150)
        //     at com.strobel.decompiler.languages.java.ast.AstBuilder.addType(AstBuilder.java:125)
        //     at com.strobel.decompiler.languages.java.JavaLanguage.buildAst(JavaLanguage.java:71)
        //     at com.strobel.decompiler.languages.java.JavaLanguage.decompileType(JavaLanguage.java:59)
        //     at com.strobel.decompiler.DecompilerDriver.decompileType(DecompilerDriver.java:330)
        //     at com.strobel.decompiler.DecompilerDriver.decompileJar(DecompilerDriver.java:251)
        //     at com.strobel.decompiler.DecompilerDriver.main(DecompilerDriver.java:126)
        // 
        throw new IllegalStateException("An error occurred while decompiling this method.");
    }
    
    public synchronized int getStoryTopicBeatCount() {
        return this.storyTopicBeatCount;
    }
    
    public void setStoryTopicBeatCount(final int p0) {
        // 
        // This method could not be decompiled.
        // 
        // Original Bytecode:
        // 
        //     3: aload_3        
        //     4: monitorexit    
        //     5: athrow         
        //     6: aload_0        
        //     7: dup            
        //     8: astore_3       
        //     9: monitorenter   
        //    10: aload_0        
        //    11: getfield        dramaman/runtime/StoryStatusWME.storyTopicBeatCount:I
        //    14: istore_2       
        //    15: aload_0        
        //    16: iload_1        
        //    17: putfield        dramaman/runtime/StoryStatusWME.storyTopicBeatCount:I
        //    20: aload_3        
        //    21: monitorexit    
        //    22: aload_0        
        //    23: getfield        dramaman/runtime/StoryStatusWME.__support:Ljava/beans/PropertyChangeSupport;
        //    26: ldc             "storyTopicBeatCount"
        //    28: iload_2        
        //    29: iload_1        
        //    30: invokevirtual   java/beans/PropertyChangeSupport.firePropertyChange:(Ljava/lang/String;II)V
        //    33: return         
        //    Exceptions:
        //  Try           Handler
        //  Start  End    Start  End    Type
        //  -----  -----  -----  -----  ----
        //  3      5      3      6      Any
        //  10     22     3      6      Any
        // 
        // The error that occurred was:
        // 
        // java.util.ConcurrentModificationException
        //     at java.util.ArrayList$Itr.checkForComodification(Unknown Source)
        //     at java.util.ArrayList$Itr.next(Unknown Source)
        //     at com.strobel.decompiler.ast.AstBuilder.convertLocalVariables(AstBuilder.java:2863)
        //     at com.strobel.decompiler.ast.AstBuilder.performStackAnalysis(AstBuilder.java:2445)
        //     at com.strobel.decompiler.ast.AstBuilder.build(AstBuilder.java:108)
        //     at com.strobel.decompiler.languages.java.ast.AstMethodBodyBuilder.createMethodBody(AstMethodBodyBuilder.java:211)
        //     at com.strobel.decompiler.languages.java.ast.AstMethodBodyBuilder.createMethodBody(AstMethodBodyBuilder.java:99)
        //     at com.strobel.decompiler.languages.java.ast.AstBuilder.createMethodBody(AstBuilder.java:782)
        //     at com.strobel.decompiler.languages.java.ast.AstBuilder.createMethod(AstBuilder.java:675)
        //     at com.strobel.decompiler.languages.java.ast.AstBuilder.addTypeMembers(AstBuilder.java:552)
        //     at com.strobel.decompiler.languages.java.ast.AstBuilder.createTypeCore(AstBuilder.java:519)
        //     at com.strobel.decompiler.languages.java.ast.AstBuilder.createTypeNoCache(AstBuilder.java:161)
        //     at com.strobel.decompiler.languages.java.ast.AstBuilder.createType(AstBuilder.java:150)
        //     at com.strobel.decompiler.languages.java.ast.AstBuilder.addType(AstBuilder.java:125)
        //     at com.strobel.decompiler.languages.java.JavaLanguage.buildAst(JavaLanguage.java:71)
        //     at com.strobel.decompiler.languages.java.JavaLanguage.decompileType(JavaLanguage.java:59)
        //     at com.strobel.decompiler.DecompilerDriver.decompileType(DecompilerDriver.java:330)
        //     at com.strobel.decompiler.DecompilerDriver.decompileJar(DecompilerDriver.java:251)
        //     at com.strobel.decompiler.DecompilerDriver.main(DecompilerDriver.java:126)
        // 
        throw new IllegalStateException("An error occurred while decompiling this method.");
    }
    
    public WMEFieldEditor _getAffinityEditor() {
        return new AffinityEditor();
    }
    
    public WMEFieldEditor _getCurrentBeatEditor() {
        return new CurrentBeatEditor();
    }
    
    public synchronized int getBeatCountOfLastGreetingBeat() {
        return this.beatCountOfLastGreetingBeat;
    }
    
    public void setBeatCountOfLastGreetingBeat(final int p0) {
        // 
        // This method could not be decompiled.
        // 
        // Original Bytecode:
        // 
        //     3: aload_3        
        //     4: monitorexit    
        //     5: athrow         
        //     6: aload_0        
        //     7: dup            
        //     8: astore_3       
        //     9: monitorenter   
        //    10: aload_0        
        //    11: getfield        dramaman/runtime/StoryStatusWME.beatCountOfLastGreetingBeat:I
        //    14: istore_2       
        //    15: aload_0        
        //    16: iload_1        
        //    17: putfield        dramaman/runtime/StoryStatusWME.beatCountOfLastGreetingBeat:I
        //    20: aload_3        
        //    21: monitorexit    
        //    22: aload_0        
        //    23: getfield        dramaman/runtime/StoryStatusWME.__support:Ljava/beans/PropertyChangeSupport;
        //    26: ldc             "beatCountOfLastGreetingBeat"
        //    28: iload_2        
        //    29: iload_1        
        //    30: invokevirtual   java/beans/PropertyChangeSupport.firePropertyChange:(Ljava/lang/String;II)V
        //    33: return         
        //    Exceptions:
        //  Try           Handler
        //  Start  End    Start  End    Type
        //  -----  -----  -----  -----  ----
        //  3      5      3      6      Any
        //  10     22     3      6      Any
        // 
        // The error that occurred was:
        // 
        // java.util.ConcurrentModificationException
        //     at java.util.ArrayList$Itr.checkForComodification(Unknown Source)
        //     at java.util.ArrayList$Itr.next(Unknown Source)
        //     at com.strobel.decompiler.ast.AstBuilder.convertLocalVariables(AstBuilder.java:2863)
        //     at com.strobel.decompiler.ast.AstBuilder.performStackAnalysis(AstBuilder.java:2445)
        //     at com.strobel.decompiler.ast.AstBuilder.build(AstBuilder.java:108)
        //     at com.strobel.decompiler.languages.java.ast.AstMethodBodyBuilder.createMethodBody(AstMethodBodyBuilder.java:211)
        //     at com.strobel.decompiler.languages.java.ast.AstMethodBodyBuilder.createMethodBody(AstMethodBodyBuilder.java:99)
        //     at com.strobel.decompiler.languages.java.ast.AstBuilder.createMethodBody(AstBuilder.java:782)
        //     at com.strobel.decompiler.languages.java.ast.AstBuilder.createMethod(AstBuilder.java:675)
        //     at com.strobel.decompiler.languages.java.ast.AstBuilder.addTypeMembers(AstBuilder.java:552)
        //     at com.strobel.decompiler.languages.java.ast.AstBuilder.createTypeCore(AstBuilder.java:519)
        //     at com.strobel.decompiler.languages.java.ast.AstBuilder.createTypeNoCache(AstBuilder.java:161)
        //     at com.strobel.decompiler.languages.java.ast.AstBuilder.createType(AstBuilder.java:150)
        //     at com.strobel.decompiler.languages.java.ast.AstBuilder.addType(AstBuilder.java:125)
        //     at com.strobel.decompiler.languages.java.JavaLanguage.buildAst(JavaLanguage.java:71)
        //     at com.strobel.decompiler.languages.java.JavaLanguage.decompileType(JavaLanguage.java:59)
        //     at com.strobel.decompiler.DecompilerDriver.decompileType(DecompilerDriver.java:330)
        //     at com.strobel.decompiler.DecompilerDriver.decompileJar(DecompilerDriver.java:251)
        //     at com.strobel.decompiler.DecompilerDriver.main(DecompilerDriver.java:126)
        // 
        throw new IllegalStateException("An error occurred while decompiling this method.");
    }
    
    public synchronized long getNLPProcessingStarted() {
        return this.NLPProcessingStarted;
    }
    
    public synchronized void setNLPProcessingStarted(final long nlpProcessingStarted) {
        this.NLPProcessingStarted = nlpProcessingStarted;
    }
    
    private final /* synthetic */ void this() {
        this.beatCount = 1;
        this.previousBeat = -1;
        this.currentBeat = -1;
        this.affinity = 0;
        this.storySegment = 1;
        this.dramaManagerEnabled = false;
        this.beatCountOfLastGreetingBeat = -1;
        this.storyTopicBeatCount = 0;
        this.NLPProcessingStarted = 0L;
    }
    
    public StoryStatusWME(final int beatCount, final int previousBeat, final int currentBeat, final int affinity, final int storySegment) {
        this.this();
        if (!StoryStatusWME.$noassert && (beatCount < 0 || previousBeat < -1 || currentBeat < -1 || affinity < 0 || affinity > -1 || storySegment < 1 || storySegment > 3)) {
            throw new AssertionError();
        }
        this.beatCount = beatCount;
        this.previousBeat = previousBeat;
        this.currentBeat = currentBeat;
        this.affinity = affinity;
        this.storySegment = storySegment;
    }
    
    public StoryStatusWME() {
        this.this();
    }
    
    static {
        $noassert = (Class.forName("[Ldramaman.runtime.StoryStatusWME;").getComponentType().desiredAssertionStatus() ^ true);
    }
    
    private class AffinityEditor extends JComboBox implements WMEFieldEditor
    {
        public String getFieldValue() {
            return Integer.toString(PrintUtilities.affinity_StringToEnum((String)this.getSelectedItem()));
        }
        
        public void setFieldValue(final String s) {
            this.setSelectedItem(PrintUtilities.affinity_EnumToString(Integer.parseInt(s)));
        }
        
        AffinityEditor() {
            super(PrintUtilities.affinity_GetEnumArray());
            this.setEditable(false);
            this.setSelectedItem(PrintUtilities.affinity_EnumToString(StoryStatusWME.this.getAffinity()));
        }
    }
    
    private class CurrentBeatEditor extends JComboBox implements WMEFieldEditor
    {
        public String getFieldValue() {
            return Integer.toString(PrintUtilities.beatID_StringToEnum((String)this.getSelectedItem()));
        }
        
        public void setFieldValue(final String s) {
            this.setSelectedItem(PrintUtilities.beatID_EnumToString(Integer.parseInt(s)));
        }
        
        CurrentBeatEditor() {
            super(PrintUtilities.beatID_GetEnumArray());
            this.setEditable(false);
            this.setSelectedItem(PrintUtilities.beatID_EnumToString(StoryStatusWME.this.getAffinity()));
        }
    }
}
